{"data":{"bookmark_timeline":{"timeline":{"instructions":[{"type":"TimelineAddEntries","entries":[{"entryId":"tweet-1530115657085644801","sortIndex":"433605062305826816","content":{"entryType":"TimelineTimelineItem","itemContent":{"itemType":"TimelineTweet","tweet_results":{"result":{"__typename":"Tweet","rest_id":"1530115657085644801","core":{"user_results":{"result":{"__typename":"User","id":"VXNlcjo5NDcwMTcyNDU1NTI2MjM2MTc=","rest_id":"947017245552623617","affiliates_highlighted_label":{},"has_nft_avatar":false,"legacy":{"blocked_by":false,"blocking":false,"can_dm":false,"can_media_tag":true,"created_at":"Sat Dec 30 08:11:20 +0000 2017","default_profile":false,"default_profile_image":false,"description":"中国人です，日本语が下手。\n不允许二次加工，转载请标明出处\n邮箱：2680647672@qq.com","entities":{"description":{"urls":[]},"url":{"urls":[{"display_url":"pixiv.net/member.php?id=…","expanded_url":"https://www.pixiv.net/member.php?id=7638711","url":"https://t.co/U774H2RlWm","indices":[0,23]}]}},"fast_followers_count":0,"favourites_count":2608,"follow_request_sent":false,"followed_by":false,"followers_count":87262,"following":false,"friends_count":789,"has_custom_timelines":false,"is_translator":false,"listed_count":783,"location":"People's Republic of China","media_count":184,"muting":false,"name":"山桂贰","normal_followers_count":87262,"notifications":false,"pinned_tweet_ids_str":["1364075670649769989"],"possibly_sensitive":false,"profile_banner_extensions":{"mediaColor":{"r":{"ok":{"palette":[{"percentage":29.56,"rgb":{"blue":225,"green":195,"red":210}},{"percentage":28.67,"rgb":{"blue":187,"green":126,"red":117}},{"percentage":9.25,"rgb":{"blue":202,"green":219,"red":255}},{"percentage":6.6,"rgb":{"blue":198,"green":161,"red":217}},{"percentage":3.87,"rgb":{"blue":249,"green":230,"red":199}}]}}}},"profile_banner_url":"https://pbs.twimg.com/profile_banners/947017245552623617/1552206013","profile_image_extensions":{"mediaColor":{"r":{"ok":{"palette":[{"percentage":58.48,"rgb":{"blue":254,"green":254,"red":254}},{"percentage":36.87,"rgb":{"blue":239,"green":236,"red":177}},{"percentage":2.39,"rgb":{"blue":199,"green":236,"red":246}},{"percentage":2.23,"rgb":{"blue":125,"green":124,"red":106}}]}}}},"profile_image_url_https":"https://pbs.twimg.com/profile_images/947018484663193600/FPitNiWs_normal.jpg","profile_interstitial_type":"","protected":false,"screen_name":"shanguier","statuses_count":375,"translator_type":"none","url":"https://t.co/U774H2RlWm","verified":false,"want_retweets":false,"withheld_in_countries":[]},"super_follow_eligible":false,"super_followed_by":false,"super_following":false}}},"unmention_info":{},"legacy":{"created_at":"Fri May 27 09:16:15 +0000 2022","conversation_id_str":"1530115657085644801","display_text_range":[0,14],"entities":{"media":[{"display_url":"pic.twitter.com/Z4mqcZemXK","expanded_url":"https://twitter.com/shanguier/status/1530115657085644801/photo/1","id_str":"1530115605491490818","indices":[15,38],"media_url_https":"https://pbs.twimg.com/media/FTwQCUqaIAIZy3V.jpg","type":"photo","url":"https://t.co/Z4mqcZemXK","features":{"large":{"faces":[{"x":42,"y":1010,"h":108,"w":108}]},"medium":{"faces":[{"x":24,"y":591,"h":63,"w":63}]},"small":{"faces":[{"x":13,"y":335,"h":35,"w":35}]},"orig":{"faces":[{"x":84,"y":2020,"h":216,"w":216}]}},"sizes":{"large":{"h":2048,"w":1260,"resize":"fit"},"medium":{"h":1200,"w":738,"resize":"fit"},"small":{"h":680,"w":418,"resize":"fit"},"thumb":{"h":150,"w":150,"resize":"crop"}},"original_info":{"height":4096,"width":2520,"focus_rects":[{"x":0,"y":1853,"w":2520,"h":1411},{"x":0,"y":1298,"w":2520,"h":2520},{"x":0,"y":1122,"w":2520,"h":2873},{"x":306,"y":0,"w":2048,"h":4096},{"x":0,"y":0,"w":2520,"h":4096}]}}],"user_mentions":[],"urls":[],"hashtags":[{"indices":[0,8],"text":"アズールレーン"}],"symbols":[]},"extended_entities":{"media":[{"display_url":"pic.twitter.com/Z4mqcZemXK","expanded_url":"https://twitter.com/shanguier/status/1530115657085644801/photo/1","id_str":"1530115605491490818","indices":[15,38],"media_key":"3_1530115605491490818","media_url_https":"https://pbs.twimg.com/media/FTwQCUqaIAIZy3V.jpg","type":"photo","url":"https://t.co/Z4mqcZemXK","ext_media_color":{"palette":[{"percentage":61.16,"rgb":{"blue":227,"green":202,"red":203}},{"percentage":9.04,"rgb":{"blue":197,"green":197,"red":247}},{"percentage":5.41,"rgb":{"blue":211,"green":153,"red":169}},{"percentage":5.23,"rgb":{"blue":87,"green":72,"red":77}},{"percentage":4.16,"rgb":{"blue":237,"green":219,"red":140}}]},"ext_media_availability":{"status":"Available"},"features":{"large":{"faces":[{"x":42,"y":1010,"h":108,"w":108}]},"medium":{"faces":[{"x":24,"y":591,"h":63,"w":63}]},"small":{"faces":[{"x":13,"y":335,"h":35,"w":35}]},"orig":{"faces":[{"x":84,"y":2020,"h":216,"w":216}]}},"sizes":{"large":{"h":2048,"w":1260,"resize":"fit"},"medium":{"h":1200,"w":738,"resize":"fit"},"small":{"h":680,"w":418,"resize":"fit"},"thumb":{"h":150,"w":150,"resize":"crop"}},"original_info":{"height":4096,"width":2520,"focus_rects":[{"x":0,"y":1853,"w":2520,"h":1411},{"x":0,"y":1298,"w":2520,"h":2520},{"x":0,"y":1122,"w":2520,"h":2873},{"x":306,"y":0,"w":2048,"h":4096},{"x":0,"y":0,"w":2520,"h":4096}]}}]},"favorite_count":34583,"favorited":false,"full_text":"#アズールレーン 五周年快乐 https://t.co/Z4mqcZemXK","is_quote_status":false,"lang":"zh","possibly_sensitive":false,"possibly_sensitive_editable":true,"quote_count":6,"reply_count":30,"retweet_count":5246,"retweeted":true,"source":"<a href=\"https://mobile.twitter.com\" rel=\"nofollow\">Twitter Web App</a>","user_id_str":"947017245552623617","id_str":"1530115657085644801"}}},"tweetDisplayType":"Tweet"}}},{"entryId":"tweet-1531763290237374466","sortIndex":"433605053006991104","content":{"entryType":"TimelineTimelineItem","itemContent":{"itemType":"TimelineTweet","tweet_results":{"result":{"__typename":"Tweet","rest_id":"1531763290237374466","core":{"user_results":{"result":{"__typename":"User","id":"VXNlcjoxMDA4MTA4ODk5MDUwNzY2MzM2","rest_id":"1008108899050766336","affiliates_highlighted_label":{},"has_nft_avatar":false,"legacy":{"blocked_by":false,"blocking":false,"can_dm":false,"can_media_tag":true,"created_at":"Sat Jun 16 22:07:46 +0000 2018","default_profile":true,"default_profile_image":false,"description":"\uD83D\uDC2C青髪と競泳水着がメインの絵描き\uD83D\uDC2C\n健康的でエロティックなものが好き。青髪キャラやオリジナルの青髪姉妹を描いてます。創作系のRT多め✨\n【活動報告】 @aigami_matome\n【FANBOX】https://t.co/p2ByJo9x2T\n【ANIFTY】https://t.co/AkMxghzaaq","entities":{"description":{"urls":[{"display_url":"garter-velvet.fanbox.cc","expanded_url":"http://garter-velvet.fanbox.cc","url":"https://t.co/p2ByJo9x2T","indices":[98,121]},{"display_url":"anifty.jp/@GATABERU","expanded_url":"http://anifty.jp/@GATABERU","url":"https://t.co/AkMxghzaaq","indices":[130,153]}]},"url":{"urls":[{"display_url":"pixiv.net/member.php?id=…","expanded_url":"https://www.pixiv.net/member.php?id=16993636","url":"https://t.co/OSteNfJVlU","indices":[0,23]}]}},"fast_followers_count":0,"favourites_count":78559,"follow_request_sent":false,"followed_by":false,"followers_count":94629,"following":false,"friends_count":1148,"has_custom_timelines":true,"is_translator":false,"listed_count":945,"location":"","media_count":566,"muting":false,"name":"がたべる\uD83D\uDC2C","normal_followers_count":94629,"notifications":false,"pinned_tweet_ids_str":["1529227389003104256"],"possibly_sensitive":true,"profile_banner_extensions":{"mediaColor":{"r":{"ok":{"palette":[{"percentage":34.16,"rgb":{"blue":181,"green":114,"red":57}},{"percentage":20.57,"rgb":{"blue":143,"green":161,"red":241}},{"percentage":16.19,"rgb":{"blue":237,"green":211,"red":233}},{"percentage":9.96,"rgb":{"blue":248,"green":209,"red":147}},{"percentage":3.42,"rgb":{"blue":250,"green":192,"red":84}}]}}}},"profile_banner_url":"https://pbs.twimg.com/profile_banners/1008108899050766336/1647557268","profile_image_extensions":{"mediaColor":{"r":{"ok":{"palette":[{"percentage":37.46,"rgb":{"blue":181,"green":200,"red":252}},{"percentage":31.02,"rgb":{"blue":169,"green":116,"red":49}},{"percentage":9.56,"rgb":{"blue":185,"green":206,"red":207}},{"percentage":6.25,"rgb":{"blue":102,"green":82,"red":69}},{"percentage":3.03,"rgb":{"blue":223,"green":194,"red":120}}]}}}},"profile_image_url_https":"https://pbs.twimg.com/profile_images/1413170075868094467/rdlDTGKl_normal.jpg","profile_interstitial_type":"","protected":false,"screen_name":"Garter_Velvet","statuses_count":67953,"translator_type":"none","url":"https://t.co/OSteNfJVlU","verified":false,"want_retweets":false,"withheld_in_countries":[]},"super_follow_eligible":false,"super_followed_by":false,"super_following":false}}},"unmention_info":{},"legacy":{"created_at":"Tue May 31 22:23:21 +0000 2022","conversation_id_str":"1531763290237374466","display_text_range":[0,48],"entities":{"media":[{"display_url":"pic.twitter.com/XWuHlRagV5","expanded_url":"https://twitter.com/Garter_Velvet/status/1531763290237374466/photo/1","id_str":"1531762739059666944","indices":[49,72],"media_url_https":"https://pbs.twimg.com/media/FUHqGHXUsAAfplz.jpg","type":"photo","url":"https://t.co/XWuHlRagV5","features":{"large":{"faces":[]},"medium":{"faces":[]},"small":{"faces":[]},"orig":{"faces":[]}},"sizes":{"large":{"h":2048,"w":1536,"resize":"fit"},"medium":{"h":1200,"w":900,"resize":"fit"},"small":{"h":680,"w":510,"resize":"fit"},"thumb":{"h":150,"w":150,"resize":"crop"}},"original_info":{"height":4096,"width":3072,"focus_rects":[{"x":0,"y":0,"w":3072,"h":1720},{"x":0,"y":0,"w":3072,"h":3072},{"x":0,"y":0,"w":3072,"h":3502},{"x":1024,"y":0,"w":2048,"h":4096},{"x":0,"y":0,"w":3072,"h":4096}]}}],"user_mentions":[],"urls":[],"hashtags":[{"indices":[0,25],"text":"6月になったのでフォロワーさんに自己紹介しようぜ"}],"symbols":[]},"extended_entities":{"media":[{"display_url":"pic.twitter.com/XWuHlRagV5","expanded_url":"https://twitter.com/Garter_Velvet/status/1531763290237374466/photo/1","id_str":"1531762739059666944","indices":[49,72],"media_key":"3_1531762739059666944","media_url_https":"https://pbs.twimg.com/media/FUHqGHXUsAAfplz.jpg","type":"photo","url":"https://t.co/XWuHlRagV5","ext_media_color":{"palette":[{"percentage":34.24,"rgb":{"blue":164,"green":182,"red":219}},{"percentage":23.81,"rgb":{"blue":102,"green":109,"red":109}},{"percentage":9.14,"rgb":{"blue":115,"green":73,"red":28}},{"percentage":8.23,"rgb":{"blue":203,"green":167,"red":50}},{"percentage":5.36,"rgb":{"blue":203,"green":193,"red":191}}]},"ext_media_availability":{"status":"Available"},"features":{"large":{"faces":[]},"medium":{"faces":[]},"small":{"faces":[]},"orig":{"faces":[]}},"sizes":{"large":{"h":2048,"w":1536,"resize":"fit"},"medium":{"h":1200,"w":900,"resize":"fit"},"small":{"h":680,"w":510,"resize":"fit"},"thumb":{"h":150,"w":150,"resize":"crop"}},"original_info":{"height":4096,"width":3072,"focus_rects":[{"x":0,"y":0,"w":3072,"h":1720},{"x":0,"y":0,"w":3072,"h":3072},{"x":0,"y":0,"w":3072,"h":3502},{"x":1024,"y":0,"w":2048,"h":4096},{"x":0,"y":0,"w":3072,"h":4096}]}}]},"favorite_count":9616,"favorited":false,"full_text":"#6月になったのでフォロワーさんに自己紹介しようぜ\n\n青髪に日焼け跡、競泳水着が好きです〜\uD83D\uDC95\uD83C\uDF1F\uD83D\uDC99 https://t.co/XWuHlRagV5","is_quote_status":false,"lang":"ja","possibly_sensitive":true,"possibly_sensitive_editable":false,"quote_count":5,"reply_count":21,"retweet_count":1410,"retweeted":false,"source":"<a href=\"https://mobile.twitter.com\" rel=\"nofollow\">Twitter Web App</a>","user_id_str":"1008108899050766336","id_str":"1531763290237374466","self_thread":{"id_str":"1531763290237374466"}}}},"tweetDisplayType":"Tweet"}}},{"entryId":"tweet-1530465253904875520","sortIndex":"433604923602319616","content":{"entryType":"TimelineTimelineItem","itemContent":{"itemType":"TimelineTweet","tweet_results":{"result":{"__typename":"Tweet","rest_id":"1530465253904875520","core":{"user_results":{"result":{"__typename":"User","id":"VXNlcjoxNDk1ODEyNzE3MTAxMjE1NzQ3","rest_id":"1495812717101215747","affiliates_highlighted_label":{},"has_nft_avatar":false,"legacy":{"blocked_by":false,"blocking":false,"can_dm":false,"can_media_tag":true,"created_at":"Mon Feb 21 17:33:10 +0000 2022","default_profile":true,"default_profile_image":false,"description":"\uD83C\uDF40FANBOX https://t.co/XZh5sEDJOl(差分・記事・CLIPデータなど)\n\uD83C\uDF40pixiv https://t.co/vj26Y7noSH\n\uD83C\uDF40神絵師でない私がTwitterフォロワーを１ヶ月半で１万人増やした方法 https://t.co/UL2rPW8nDV","entities":{"description":{"urls":[{"display_url":"umemoto.fanbox.cc","expanded_url":"http://umemoto.fanbox.cc","url":"https://t.co/XZh5sEDJOl","indices":[8,31]},{"display_url":"pixiv.net/users/39072474","expanded_url":"http://pixiv.net/users/39072474","url":"https://t.co/vj26Y7noSH","indices":[56,79]},{"display_url":"umemoto.fanbox.cc/posts/3690187","expanded_url":"http://umemoto.fanbox.cc/posts/3690187","url":"https://t.co/UL2rPW8nDV","indices":[117,140]}]},"url":{"urls":[{"display_url":"umemoto01.booth.pm","expanded_url":"https://umemoto01.booth.pm/","url":"https://t.co/Zx34M5mW4T","indices":[0,23]}]}},"fast_followers_count":0,"favourites_count":192,"follow_request_sent":false,"followed_by":false,"followers_count":47757,"following":false,"friends_count":322,"has_custom_timelines":false,"is_translator":false,"listed_count":291,"location":"","media_count":71,"muting":false,"name":"うめもと\uD83D\uDD1E同人・FANBOX","normal_followers_count":47757,"notifications":false,"pinned_tweet_ids_str":["1496562420042854401"],"possibly_sensitive":true,"profile_banner_extensions":{"mediaColor":{"r":{"ok":{"palette":[{"percentage":81.61,"rgb":{"blue":1,"green":200,"red":255}},{"percentage":12.99,"rgb":{"blue":254,"green":255,"red":255}},{"percentage":3.51,"rgb":{"blue":181,"green":238,"red":255}},{"percentage":1.62,"rgb":{"blue":116,"green":225,"red":255}}]}}}},"profile_banner_url":"https://pbs.twimg.com/profile_banners/1495812717101215747/1646321592","profile_image_extensions":{"mediaColor":{"r":{"ok":{"palette":[{"percentage":69.62,"rgb":{"blue":166,"green":198,"red":211}},{"percentage":18.82,"rgb":{"blue":92,"green":135,"red":153}},{"percentage":5.47,"rgb":{"blue":83,"green":99,"red":111}},{"percentage":1.25,"rgb":{"blue":165,"green":199,"red":209}},{"percentage":0.99,"rgb":{"blue":114,"green":15,"red":8}}]}}}},"profile_image_url_https":"https://pbs.twimg.com/profile_images/1511290559050428417/U_LdiJFo_normal.jpg","profile_interstitial_type":"sensitive_media","protected":false,"screen_name":"umemoto_18","statuses_count":22040,"translator_type":"none","url":"https://t.co/Zx34M5mW4T","verified":false,"want_retweets":false,"withheld_in_countries":[]},"super_follow_eligible":false,"super_followed_by":false,"super_following":false}}},"unmention_info":{},"legacy":{"created_at":"Sat May 28 08:25:25 +0000 2022","conversation_id_str":"1530465253904875520","display_text_range":[0,28],"entities":{"media":[{"display_url":"pic.twitter.com/vZEbxUAizp","expanded_url":"https://twitter.com/umemoto_18/status/1530465253904875520/photo/1","id_str":"1530465100661813248","indices":[29,52],"media_url_https":"https://pbs.twimg.com/media/FT1N5noUcAAkTOi.jpg","type":"photo","url":"https://t.co/vZEbxUAizp","features":{"large":{"faces":[{"x":459,"y":204,"h":179,"w":179}]},"medium":{"faces":[{"x":389,"y":173,"h":151,"w":151}]},"small":{"faces":[{"x":220,"y":98,"h":86,"w":86}]},"orig":{"faces":[{"x":459,"y":204,"h":179,"w":179}]}},"sizes":{"large":{"h":1414,"w":1000,"resize":"fit"},"medium":{"h":1200,"w":849,"resize":"fit"},"small":{"h":680,"w":481,"resize":"fit"},"thumb":{"h":150,"w":150,"resize":"crop"}},"original_info":{"height":1414,"width":1000,"focus_rects":[{"x":0,"y":38,"w":1000,"h":560},{"x":0,"y":0,"w":1000,"h":1000},{"x":0,"y":0,"w":1000,"h":1140},{"x":106,"y":0,"w":707,"h":1414},{"x":0,"y":0,"w":1000,"h":1414}]}},{"display_url":"pic.twitter.com/vZEbxUAizp","expanded_url":"https://twitter.com/umemoto_18/status/1530465253904875520/photo/1","id_str":"1530465138330914816","indices":[29,52],"media_url_https":"https://pbs.twimg.com/media/FT1N7z9VUAAM17m.jpg","type":"photo","url":"https://t.co/vZEbxUAizp","features":{"large":{"faces":[]},"medium":{"faces":[]},"small":{"faces":[]},"orig":{"faces":[]}},"sizes":{"large":{"h":1414,"w":1000,"resize":"fit"},"medium":{"h":1200,"w":849,"resize":"fit"},"small":{"h":680,"w":481,"resize":"fit"},"thumb":{"h":150,"w":150,"resize":"crop"}},"original_info":{"height":1414,"width":1000,"focus_rects":[{"x":0,"y":854,"w":1000,"h":560},{"x":0,"y":414,"w":1000,"h":1000},{"x":0,"y":274,"w":1000,"h":1140},{"x":0,"y":0,"w":707,"h":1414},{"x":0,"y":0,"w":1000,"h":1414}]}},{"display_url":"pic.twitter.com/vZEbxUAizp","expanded_url":"https://twitter.com/umemoto_18/status/1530465253904875520/photo/1","id_str":"1530465190004723712","indices":[29,52],"media_url_https":"https://pbs.twimg.com/media/FT1N-0dVEAAcyKH.jpg","type":"photo","url":"https://t.co/vZEbxUAizp","features":{"large":{"faces":[{"x":740,"y":484,"h":205,"w":205},{"x":5,"y":979,"h":283,"w":283}]},"medium":{"faces":[{"x":628,"y":410,"h":174,"w":174},{"x":4,"y":831,"h":240,"w":240}]},"small":{"faces":[{"x":355,"y":232,"h":98,"w":98},{"x":2,"y":470,"h":136,"w":136}]},"orig":{"faces":[{"x":740,"y":484,"h":205,"w":205},{"x":5,"y":979,"h":283,"w":283}]}},"sizes":{"large":{"h":1414,"w":1000,"resize":"fit"},"medium":{"h":1200,"w":849,"resize":"fit"},"small":{"h":680,"w":481,"resize":"fit"},"thumb":{"h":150,"w":150,"resize":"crop"}},"original_info":{"height":1414,"width":1000,"focus_rects":[{"x":0,"y":0,"w":1000,"h":560},{"x":0,"y":0,"w":1000,"h":1000},{"x":0,"y":0,"w":1000,"h":1140},{"x":293,"y":0,"w":707,"h":1414},{"x":0,"y":0,"w":1000,"h":1414}]}},{"display_url":"pic.twitter.com/vZEbxUAizp","expanded_url":"https://twitter.com/umemoto_18/status/1530465253904875520/photo/1","id_str":"1530465228151934976","indices":[29,52],"media_url_https":"https://pbs.twimg.com/media/FT1OBCkVUAAyjm5.jpg","type":"photo","url":"https://t.co/vZEbxUAizp","features":{"large":{"faces":[]},"medium":{"faces":[]},"small":{"faces":[]},"orig":{"faces":[]}},"sizes":{"large":{"h":1414,"w":1000,"resize":"fit"},"medium":{"h":1200,"w":849,"resize":"fit"},"small":{"h":680,"w":481,"resize":"fit"},"thumb":{"h":150,"w":150,"resize":"crop"}},"original_info":{"height":1414,"width":1000,"focus_rects":[{"x":0,"y":0,"w":1000,"h":560},{"x":0,"y":0,"w":1000,"h":1000},{"x":0,"y":0,"w":1000,"h":1140},{"x":293,"y":0,"w":707,"h":1414},{"x":0,"y":0,"w":1000,"h":1414}]}}],"user_mentions":[],"urls":[],"hashtags":[{"indices":[0,16],"text":"自分が何度も投稿してしまう画像"}],"symbols":[]},"extended_entities":{"media":[{"display_url":"pic.twitter.com/vZEbxUAizp","expanded_url":"https://twitter.com/umemoto_18/status/1530465253904875520/photo/1","id_str":"1530465100661813248","indices":[29,52],"media_key":"3_1530465100661813248","media_url_https":"https://pbs.twimg.com/media/FT1N5noUcAAkTOi.jpg","type":"photo","url":"https://t.co/vZEbxUAizp","ext_media_color":{"palette":[{"percentage":55.69,"rgb":{"blue":118,"green":140,"red":202}},{"percentage":9.75,"rgb":{"blue":196,"green":218,"red":232}},{"percentage":9.35,"rgb":{"blue":70,"green":71,"red":74}},{"percentage":7.65,"rgb":{"blue":62,"green":89,"red":143}},{"percentage":3.58,"rgb":{"blue":93,"green":120,"red":227}}]},"ext_media_availability":{"status":"Available"},"features":{"large":{"faces":[{"x":459,"y":204,"h":179,"w":179}]},"medium":{"faces":[{"x":389,"y":173,"h":151,"w":151}]},"small":{"faces":[{"x":220,"y":98,"h":86,"w":86}]},"orig":{"faces":[{"x":459,"y":204,"h":179,"w":179}]}},"sizes":{"large":{"h":1414,"w":1000,"resize":"fit"},"medium":{"h":1200,"w":849,"resize":"fit"},"small":{"h":680,"w":481,"resize":"fit"},"thumb":{"h":150,"w":150,"resize":"crop"}},"original_info":{"height":1414,"width":1000,"focus_rects":[{"x":0,"y":38,"w":1000,"h":560},{"x":0,"y":0,"w":1000,"h":1000},{"x":0,"y":0,"w":1000,"h":1140},{"x":106,"y":0,"w":707,"h":1414},{"x":0,"y":0,"w":1000,"h":1414}]}},{"display_url":"pic.twitter.com/vZEbxUAizp","expanded_url":"https://twitter.com/umemoto_18/status/1530465253904875520/photo/1","id_str":"1530465138330914816","indices":[29,52],"media_key":"3_1530465138330914816","media_url_https":"https://pbs.twimg.com/media/FT1N7z9VUAAM17m.jpg","type":"photo","url":"https://t.co/vZEbxUAizp","ext_media_color":{"palette":[{"percentage":42.6,"rgb":{"blue":192,"green":201,"red":225}},{"percentage":26.3,"rgb":{"blue":108,"green":142,"red":204}},{"percentage":10.85,"rgb":{"blue":99,"green":71,"red":67}},{"percentage":3.71,"rgb":{"blue":54,"green":92,"red":134}},{"percentage":2.68,"rgb":{"blue":83,"green":114,"red":200}}]},"ext_media_availability":{"status":"Available"},"features":{"large":{"faces":[]},"medium":{"faces":[]},"small":{"faces":[]},"orig":{"faces":[]}},"sizes":{"large":{"h":1414,"w":1000,"resize":"fit"},"medium":{"h":1200,"w":849,"resize":"fit"},"small":{"h":680,"w":481,"resize":"fit"},"thumb":{"h":150,"w":150,"resize":"crop"}},"original_info":{"height":1414,"width":1000,"focus_rects":[{"x":0,"y":854,"w":1000,"h":560},{"x":0,"y":414,"w":1000,"h":1000},{"x":0,"y":274,"w":1000,"h":1140},{"x":0,"y":0,"w":707,"h":1414},{"x":0,"y":0,"w":1000,"h":1414}]}},{"display_url":"pic.twitter.com/vZEbxUAizp","expanded_url":"https://twitter.com/umemoto_18/status/1530465253904875520/photo/1","id_str":"1530465190004723712","indices":[29,52],"media_key":"3_1530465190004723712","media_url_https":"https://pbs.twimg.com/media/FT1N-0dVEAAcyKH.jpg","type":"photo","url":"https://t.co/vZEbxUAizp","ext_media_color":{"palette":[{"percentage":43.7,"rgb":{"blue":95,"green":104,"red":156}},{"percentage":39.25,"rgb":{"blue":206,"green":220,"red":235}},{"percentage":3.55,"rgb":{"blue":139,"green":171,"red":216}},{"percentage":3.09,"rgb":{"blue":76,"green":79,"red":155}},{"percentage":2.2,"rgb":{"blue":235,"green":216,"red":166}}]},"ext_media_availability":{"status":"Available"},"features":{"large":{"faces":[{"x":740,"y":484,"h":205,"w":205},{"x":5,"y":979,"h":283,"w":283}]},"medium":{"faces":[{"x":628,"y":410,"h":174,"w":174},{"x":4,"y":831,"h":240,"w":240}]},"small":{"faces":[{"x":355,"y":232,"h":98,"w":98},{"x":2,"y":470,"h":136,"w":136}]},"orig":{"faces":[{"x":740,"y":484,"h":205,"w":205},{"x":5,"y":979,"h":283,"w":283}]}},"sizes":{"large":{"h":1414,"w":1000,"resize":"fit"},"medium":{"h":1200,"w":849,"resize":"fit"},"small":{"h":680,"w":481,"resize":"fit"},"thumb":{"h":150,"w":150,"resize":"crop"}},"original_info":{"height":1414,"width":1000,"focus_rects":[{"x":0,"y":0,"w":1000,"h":560},{"x":0,"y":0,"w":1000,"h":1000},{"x":0,"y":0,"w":1000,"h":1140},{"x":293,"y":0,"w":707,"h":1414},{"x":0,"y":0,"w":1000,"h":1414}]}},{"display_url":"pic.twitter.com/vZEbxUAizp","expanded_url":"https://twitter.com/umemoto_18/status/1530465253904875520/photo/1","id_str":"1530465228151934976","indices":[29,52],"media_key":"3_1530465228151934976","media_url_https":"https://pbs.twimg.com/media/FT1OBCkVUAAyjm5.jpg","type":"photo","url":"https://t.co/vZEbxUAizp","ext_media_color":{"palette":[{"percentage":53.78,"rgb":{"blue":82,"green":104,"red":159}},{"percentage":28.85,"rgb":{"blue":181,"green":197,"red":224}},{"percentage":3.65,"rgb":{"blue":118,"green":146,"red":202}},{"percentage":3.6,"rgb":{"blue":28,"green":41,"red":87}},{"percentage":2.05,"rgb":{"blue":64,"green":86,"red":168}}]},"ext_media_availability":{"status":"Available"},"features":{"large":{"faces":[]},"medium":{"faces":[]},"small":{"faces":[]},"orig":{"faces":[]}},"sizes":{"large":{"h":1414,"w":1000,"resize":"fit"},"medium":{"h":1200,"w":849,"resize":"fit"},"small":{"h":680,"w":481,"resize":"fit"},"thumb":{"h":150,"w":150,"resize":"crop"}},"original_info":{"height":1414,"width":1000,"focus_rects":[{"x":0,"y":0,"w":1000,"h":560},{"x":0,"y":0,"w":1000,"h":1000},{"x":0,"y":0,"w":1000,"h":1140},{"x":293,"y":0,"w":707,"h":1414},{"x":0,"y":0,"w":1000,"h":1414}]}}]},"favorite_count":12284,"favorited":false,"full_text":"#自分が何度も投稿してしまう画像 \n喜多川海夢さんまとめ https://t.co/vZEbxUAizp","is_quote_status":false,"lang":"ja","possibly_sensitive":true,"possibly_sensitive_editable":false,"quote_count":1,"reply_count":13,"retweet_count":2072,"retweeted":false,"source":"<a href=\"https://mobile.twitter.com\" rel=\"nofollow\">Twitter Web App</a>","user_id_str":"1495812717101215747","id_str":"1530465253904875520","self_thread":{"id_str":"1530465253904875520"}}}},"tweetDisplayType":"Tweet"}}},{"entryId":"tweet-1500108392865488902","sortIndex":"433601099984098304","content":{"entryType":"TimelineTimelineItem","itemContent":{"itemType":"TimelineTweet","tweet_results":{"result":{"__typename":"Tweet","rest_id":"1500108392865488902","core":{"user_results":{"result":{"__typename":"User","id":"VXNlcjo4Nzg1MzA1NTM2NDkxNTIwMDA=","rest_id":"878530553649152000","affiliates_highlighted_label":{},"has_nft_avatar":false,"legacy":{"blocked_by":false,"blocking":false,"can_dm":true,"can_media_tag":true,"created_at":"Sat Jun 24 08:29:41 +0000 2017","default_profile":false,"default_profile_image":false,"description":"!FANBOX!:https://t.co/AVKOrc5hkv\n\n외주문의는 트위터dm으로","entities":{"description":{"urls":[{"display_url":"qhrrb3409.fanbox.cc","expanded_url":"http://qhrrb3409.fanbox.cc","url":"https://t.co/AVKOrc5hkv","indices":[9,32]}]},"url":{"urls":[{"display_url":"twitch.tv/qhrrb3409","expanded_url":"https://www.twitch.tv/qhrrb3409","url":"https://t.co/4Ub9FTVgcV","indices":[0,23]}]}},"fast_followers_count":0,"favourites_count":830,"follow_request_sent":false,"followed_by":false,"followers_count":53828,"following":false,"friends_count":279,"has_custom_timelines":false,"is_translator":false,"listed_count":360,"location":"","media_count":154,"muting":false,"name":"bbolalus","normal_followers_count":53828,"notifications":false,"pinned_tweet_ids_str":["1493219975623942148"],"possibly_sensitive":false,"profile_banner_extensions":{"mediaColor":{"r":{"ok":{"palette":[{"percentage":37.59,"rgb":{"blue":72,"green":73,"red":73}},{"percentage":35.3,"rgb":{"blue":234,"green":234,"red":234}}]}}}},"profile_banner_url":"https://pbs.twimg.com/profile_banners/878530553649152000/1635502579","profile_image_extensions":{"mediaColor":{"r":{"ok":{"palette":[{"percentage":47.29,"rgb":{"blue":125,"green":107,"red":159}},{"percentage":36.1,"rgb":{"blue":119,"green":101,"red":111}},{"percentage":10.8,"rgb":{"blue":187,"green":184,"red":200}},{"percentage":2.36,"rgb":{"blue":74,"green":52,"red":185}},{"percentage":2.05,"rgb":{"blue":34,"green":26,"red":54}}]}}}},"profile_image_url_https":"https://pbs.twimg.com/profile_images/1493689768613318656/oywKLtFg_normal.jpg","profile_interstitial_type":"","protected":false,"screen_name":"qhrrb3409","statuses_count":587,"translator_type":"none","url":"https://t.co/4Ub9FTVgcV","verified":false,"want_retweets":false,"withheld_in_countries":[]},"super_follow_eligible":false,"super_followed_by":false,"super_following":false}}},"unmention_info":{},"legacy":{"created_at":"Sat Mar 05 13:58:06 +0000 2022","conversation_id_str":"1500108392865488902","display_text_range":[0,32],"entities":{"media":[{"display_url":"pic.twitter.com/Q8R3vEemTb","expanded_url":"https://twitter.com/qhrrb3409/status/1500108392865488902/photo/1","id_str":"1500107741397864448","indices":[33,56],"media_url_https":"https://pbs.twimg.com/media/FNF0CvrVUAAS5r7.jpg","type":"photo","url":"https://t.co/Q8R3vEemTb","features":{"large":{"faces":[]},"medium":{"faces":[]},"small":{"faces":[]},"orig":{"faces":[]}},"sizes":{"large":{"h":2048,"w":1638,"resize":"fit"},"medium":{"h":1200,"w":960,"resize":"fit"},"small":{"h":680,"w":544,"resize":"fit"},"thumb":{"h":150,"w":150,"resize":"crop"}},"original_info":{"height":3789,"width":3031,"focus_rects":[{"x":0,"y":383,"w":3031,"h":1697},{"x":0,"y":0,"w":3031,"h":3031},{"x":0,"y":0,"w":3031,"h":3455},{"x":284,"y":0,"w":1895,"h":3789},{"x":0,"y":0,"w":3031,"h":3789}]}}],"user_mentions":[],"urls":[],"hashtags":[],"symbols":[]},"extended_entities":{"media":[{"display_url":"pic.twitter.com/Q8R3vEemTb","expanded_url":"https://twitter.com/qhrrb3409/status/1500108392865488902/photo/1","id_str":"1500107741397864448","indices":[33,56],"media_key":"3_1500107741397864448","media_url_https":"https://pbs.twimg.com/media/FNF0CvrVUAAS5r7.jpg","type":"photo","url":"https://t.co/Q8R3vEemTb","ext_media_color":{"palette":[{"percentage":55.38,"rgb":{"blue":156,"green":150,"red":164}},{"percentage":25.71,"rgb":{"blue":58,"green":52,"red":63}},{"percentage":3.13,"rgb":{"blue":122,"green":103,"red":95}},{"percentage":1.7,"rgb":{"blue":114,"green":112,"red":155}},{"percentage":1.0,"rgb":{"blue":227,"green":197,"red":191}}]},"ext_media_availability":{"status":"Available"},"features":{"large":{"faces":[]},"medium":{"faces":[]},"small":{"faces":[]},"orig":{"faces":[]}},"sizes":{"large":{"h":2048,"w":1638,"resize":"fit"},"medium":{"h":1200,"w":960,"resize":"fit"},"small":{"h":680,"w":544,"resize":"fit"},"thumb":{"h":150,"w":150,"resize":"crop"}},"original_info":{"height":3789,"width":3031,"focus_rects":[{"x":0,"y":383,"w":3031,"h":1697},{"x":0,"y":0,"w":3031,"h":3031},{"x":0,"y":0,"w":3031,"h":3455},{"x":284,"y":0,"w":1895,"h":3789},{"x":0,"y":0,"w":3031,"h":3789}]}}]},"favorite_count":6490,"favorited":false,"full_text":"노벨피아 소설 '회귀자가 기연을 분양함' 외주 작업물입니다 https://t.co/Q8R3vEemTb","is_quote_status":false,"lang":"ko","possibly_sensitive":true,"possibly_sensitive_editable":false,"quote_count":1,"reply_count":10,"retweet_count":993,"retweeted":false,"source":"<a href=\"https://mobile.twitter.com\" rel=\"nofollow\">Twitter Web App</a>","user_id_str":"878530553649152000","id_str":"1500108392865488902"}}},"tweetDisplayType":"Tweet"}}},{"entryId":"tweet-1531236892918050818","sortIndex":"433601079061290240","content":{"entryType":"TimelineTimelineItem","itemContent":{"itemType":"TimelineTweet","tweet_results":{"result":{"__typename":"Tweet","rest_id":"1531236892918050818","core":{"user_results":{"result":{"__typename":"User","id":"VXNlcjoxMDc4ODYzMzk2NTYzMzY5OTg0","rest_id":"1078863396563369984","affiliates_highlighted_label":{},"has_nft_avatar":false,"legacy":{"blocked_by":false,"blocking":false,"can_dm":false,"can_media_tag":true,"created_at":"Sat Dec 29 04:00:52 +0000 2018","default_profile":false,"default_profile_image":false,"description":"ほっぺを吸いたい。リプ返あんまりできません FANBOX、詳しいのは→（https://t.co/I18vmYJPu9）ピクシブ→https://t.co/R4CctJg3DH skeb→（https://t.co/Qxg2BRmI4T）","entities":{"description":{"urls":[{"display_url":"nephthys.fanbox.cc","expanded_url":"http://nephthys.fanbox.cc","url":"https://t.co/I18vmYJPu9","indices":[36,59]},{"display_url":"pixiv.net/users/39266985","expanded_url":"http://pixiv.net/users/39266985","url":"https://t.co/R4CctJg3DH","indices":[65,88]},{"display_url":"skeb.jp/@OW33166620","expanded_url":"http://skeb.jp/@OW33166620","url":"https://t.co/Qxg2BRmI4T","indices":[95,118]}]}},"fast_followers_count":0,"favourites_count":66292,"follow_request_sent":false,"followed_by":false,"followers_count":274775,"following":false,"friends_count":5827,"has_custom_timelines":true,"is_translator":false,"listed_count":2126,"location":"あなたの後ろ","media_count":232,"muting":false,"name":"ねふ","normal_followers_count":274775,"notifications":false,"pinned_tweet_ids_str":["1531236892918050818"],"possibly_sensitive":false,"profile_banner_extensions":{"mediaColor":{"r":{"ok":{"palette":[{"percentage":49.07,"rgb":{"blue":216,"green":217,"red":239}},{"percentage":24.35,"rgb":{"blue":123,"green":128,"red":213}},{"percentage":9.87,"rgb":{"blue":154,"green":133,"red":192}},{"percentage":3.8,"rgb":{"blue":194,"green":158,"red":191}},{"percentage":2.13,"rgb":{"blue":92,"green":145,"red":211}}]}}}},"profile_banner_url":"https://pbs.twimg.com/profile_banners/1078863396563369984/1646655492","profile_image_extensions":{"mediaColor":{"r":{"ok":{"palette":[{"percentage":67.74,"rgb":{"blue":177,"green":185,"red":215}},{"percentage":13.67,"rgb":{"blue":113,"green":121,"red":153}},{"percentage":8.62,"rgb":{"blue":47,"green":35,"red":40}},{"percentage":6.77,"rgb":{"blue":148,"green":161,"red":238}},{"percentage":1.78,"rgb":{"blue":160,"green":136,"red":124}}]}}}},"profile_image_url_https":"https://pbs.twimg.com/profile_images/1461601281651666947/psxOEolS_normal.jpg","profile_interstitial_type":"","protected":false,"screen_name":"OW33166620","statuses_count":72968,"translator_type":"none","verified":false,"want_retweets":false,"withheld_in_countries":[]},"super_follow_eligible":false,"super_followed_by":false,"super_following":false}}},"unmention_info":{},"legacy":{"created_at":"Mon May 30 11:31:38 +0000 2022","conversation_id_str":"1531236892918050818","display_text_range":[0,1],"entities":{"media":[{"display_url":"pic.twitter.com/NkUCtGUKS1","expanded_url":"https://twitter.com/OW33166620/status/1531236892918050818/photo/1","id_str":"1531236822449541122","indices":[2,25],"media_url_https":"https://pbs.twimg.com/media/FUALxvUaUAIPQ8C.jpg","type":"photo","url":"https://t.co/NkUCtGUKS1","features":{"large":{"faces":[]},"medium":{"faces":[]},"small":{"faces":[]},"orig":{"faces":[]}},"sizes":{"large":{"h":1368,"w":813,"resize":"fit"},"medium":{"h":1200,"w":713,"resize":"fit"},"small":{"h":680,"w":404,"resize":"fit"},"thumb":{"h":150,"w":150,"resize":"crop"}},"original_info":{"height":1368,"width":813,"focus_rects":[{"x":0,"y":149,"w":813,"h":455},{"x":0,"y":0,"w":813,"h":813},{"x":0,"y":0,"w":813,"h":927},{"x":34,"y":0,"w":684,"h":1368},{"x":0,"y":0,"w":813,"h":1368}]}}],"user_mentions":[],"urls":[],"hashtags":[],"symbols":[]},"extended_entities":{"media":[{"display_url":"pic.twitter.com/NkUCtGUKS1","expanded_url":"https://twitter.com/OW33166620/status/1531236892918050818/photo/1","id_str":"1531236822449541122","indices":[2,25],"media_key":"3_1531236822449541122","media_url_https":"https://pbs.twimg.com/media/FUALxvUaUAIPQ8C.jpg","type":"photo","url":"https://t.co/NkUCtGUKS1","ext_media_color":{"palette":[{"percentage":81.66,"rgb":{"blue":255,"green":255,"red":255}},{"percentage":7.11,"rgb":{"blue":69,"green":68,"red":70}},{"percentage":2.59,"rgb":{"blue":114,"green":116,"red":147}},{"percentage":1.95,"rgb":{"blue":128,"green":129,"red":138}}]},"ext_media_availability":{"status":"Available"},"features":{"large":{"faces":[]},"medium":{"faces":[]},"small":{"faces":[]},"orig":{"faces":[]}},"sizes":{"large":{"h":1368,"w":813,"resize":"fit"},"medium":{"h":1200,"w":713,"resize":"fit"},"small":{"h":680,"w":404,"resize":"fit"},"thumb":{"h":150,"w":150,"resize":"crop"}},"original_info":{"height":1368,"width":813,"focus_rects":[{"x":0,"y":149,"w":813,"h":455},{"x":0,"y":0,"w":813,"h":813},{"x":0,"y":0,"w":813,"h":927},{"x":34,"y":0,"w":684,"h":1368},{"x":0,"y":0,"w":813,"h":1368}]}}]},"favorite_count":26196,"favorited":false,"full_text":"\uD83E\uDEE5 https://t.co/NkUCtGUKS1","is_quote_status":false,"lang":"und","possibly_sensitive":true,"possibly_sensitive_editable":false,"quote_count":12,"reply_count":44,"retweet_count":4505,"retweeted":true,"source":"<a href=\"https://mobile.twitter.com\" rel=\"nofollow\">Twitter Web App</a>","user_id_str":"1078863396563369984","id_str":"1531236892918050818"}}},"tweetDisplayType":"Tweet"}}},{"entryId":"tweet-1531647101339193347","sortIndex":"433600618534962944","content":{"entryType":"TimelineTimelineItem","itemContent":{"itemType":"TimelineTweet","tweet_results":{"result":{"__typename":"Tweet","rest_id":"1531647101339193347","core":{"user_results":{"result":{"__typename":"User","id":"VXNlcjoxMDA1ODAzODgxNTEzNjM5OTM2","rest_id":"1005803881513639936","affiliates_highlighted_label":{},"has_nft_avatar":false,"legacy":{"blocked_by":false,"blocking":false,"can_dm":true,"can_media_tag":true,"created_at":"Sun Jun 10 13:28:27 +0000 2018","default_profile":true,"default_profile_image":false,"description":"Contact : ary589@naver.com\n아트코벤트 강사\nVtuber design : @chashas2\n\nFANBOX : https://t.co/QhRj6PA0Eu\n팬딩 : https://t.co/3gqELhMSOW","entities":{"description":{"urls":[{"display_url":"msh.fanbox.cc","expanded_url":"http://msh.fanbox.cc","url":"https://t.co/QhRj6PA0Eu","indices":[72,95]},{"display_url":"fanding.kr/user/msh589","expanded_url":"https://fanding.kr/user/msh589","url":"https://t.co/3gqELhMSOW","indices":[101,124]}]},"url":{"urls":[{"display_url":"pixiv.net/member.php?id=…","expanded_url":"https://www.pixiv.net/member.php?id=4091289","url":"https://t.co/Tr22dChu8R","indices":[0,23]}]}},"fast_followers_count":0,"favourites_count":1313,"follow_request_sent":false,"followed_by":false,"followers_count":54095,"following":false,"friends_count":617,"has_custom_timelines":true,"is_translator":false,"listed_count":480,"location":"","media_count":125,"muting":false,"name":"msh","normal_followers_count":54095,"notifications":false,"pinned_tweet_ids_str":["1432650716976279556"],"possibly_sensitive":true,"profile_banner_extensions":{"mediaColor":{"r":{"ok":{"palette":[{"percentage":52.09,"rgb":{"blue":165,"green":175,"red":214}},{"percentage":12.74,"rgb":{"blue":94,"green":96,"red":140}},{"percentage":11.65,"rgb":{"blue":101,"green":117,"red":197}},{"percentage":11.3,"rgb":{"blue":136,"green":126,"red":140}},{"percentage":4.65,"rgb":{"blue":88,"green":66,"red":71}}]}}}},"profile_banner_url":"https://pbs.twimg.com/profile_banners/1005803881513639936/1594116718","profile_image_extensions":{"mediaColor":{"r":{"ok":{"palette":[{"percentage":81.75,"rgb":{"blue":237,"green":239,"red":249}},{"percentage":7.24,"rgb":{"blue":227,"green":189,"red":174}},{"percentage":2.26,"rgb":{"blue":73,"green":71,"red":73}},{"percentage":2.25,"rgb":{"blue":225,"green":158,"red":119}},{"percentage":1.1,"rgb":{"blue":236,"green":249,"red":247}}]}}}},"profile_image_url_https":"https://pbs.twimg.com/profile_images/1229961617590247425/Nn-LV3ET_normal.jpg","profile_interstitial_type":"","protected":false,"screen_name":"moon_mro","statuses_count":1517,"translator_type":"none","url":"https://t.co/Tr22dChu8R","verified":false,"want_retweets":false,"withheld_in_countries":[]},"super_follow_eligible":false,"super_followed_by":false,"super_following":false}}},"unmention_info":{},"legacy":{"created_at":"Tue May 31 14:41:40 +0000 2022","conversation_id_str":"1531647101339193347","display_text_range":[0,4],"entities":{"media":[{"display_url":"pic.twitter.com/izV8qt4c1R","expanded_url":"https://twitter.com/moon_mro/status/1531647101339193347/photo/1","id_str":"1531645889910931456","indices":[5,28],"media_url_https":"https://pbs.twimg.com/media/FUF_0mXUAAArAuT.jpg","type":"photo","url":"https://t.co/izV8qt4c1R","features":{"large":{"faces":[]},"medium":{"faces":[]},"small":{"faces":[]},"orig":{"faces":[]}},"sizes":{"large":{"h":2048,"w":1613,"resize":"fit"},"medium":{"h":1200,"w":945,"resize":"fit"},"small":{"h":680,"w":536,"resize":"fit"},"thumb":{"h":150,"w":150,"resize":"crop"}},"original_info":{"height":4096,"width":3226,"focus_rects":[{"x":0,"y":837,"w":3226,"h":1807},{"x":0,"y":127,"w":3226,"h":3226},{"x":0,"y":0,"w":3226,"h":3678},{"x":1126,"y":0,"w":2048,"h":4096},{"x":0,"y":0,"w":3226,"h":4096}]}}],"user_mentions":[],"urls":[],"hashtags":[],"symbols":[]},"extended_entities":{"media":[{"display_url":"pic.twitter.com/izV8qt4c1R","expanded_url":"https://twitter.com/moon_mro/status/1531647101339193347/photo/1","id_str":"1531645889910931456","indices":[5,28],"media_key":"3_1531645889910931456","media_url_https":"https://pbs.twimg.com/media/FUF_0mXUAAArAuT.jpg","type":"photo","url":"https://t.co/izV8qt4c1R","ext_media_color":{"palette":[{"percentage":71.47,"rgb":{"blue":187,"green":189,"red":222}},{"percentage":14.39,"rgb":{"blue":135,"green":119,"red":89}},{"percentage":4.91,"rgb":{"blue":115,"green":147,"red":191}},{"percentage":4.26,"rgb":{"blue":117,"green":128,"red":157}},{"percentage":2.33,"rgb":{"blue":229,"green":219,"red":199}}]},"ext_media_availability":{"status":"Available"},"features":{"large":{"faces":[]},"medium":{"faces":[]},"small":{"faces":[]},"orig":{"faces":[]}},"sizes":{"large":{"h":2048,"w":1613,"resize":"fit"},"medium":{"h":1200,"w":945,"resize":"fit"},"small":{"h":680,"w":536,"resize":"fit"},"thumb":{"h":150,"w":150,"resize":"crop"}},"original_info":{"height":4096,"width":3226,"focus_rects":[{"x":0,"y":837,"w":3226,"h":1807},{"x":0,"y":127,"w":3226,"h":3226},{"x":0,"y":0,"w":3226,"h":3678},{"x":1126,"y":0,"w":2048,"h":4096},{"x":0,"y":0,"w":3226,"h":4096}]}}]},"favorite_count":3839,"favorited":false,"full_text":"水着♥️ https://t.co/izV8qt4c1R","is_quote_status":false,"lang":"ja","possibly_sensitive":true,"possibly_sensitive_editable":false,"quote_count":2,"reply_count":2,"retweet_count":677,"retweeted":true,"source":"<a href=\"https://mobile.twitter.com\" rel=\"nofollow\">Twitter Web App</a>","user_id_str":"1005803881513639936","id_str":"1531647101339193347"}}},"tweetDisplayType":"Tweet"}}},{"entryId":"tweet-1531413773524684801","sortIndex":"433580327767278848","content":{"entryType":"TimelineTimelineItem","itemContent":{"itemType":"TimelineTweet","tweet_results":{"result":{"__typename":"Tweet","rest_id":"1531413773524684801","core":{"user_results":{"result":{"__typename":"User","id":"VXNlcjo3NDA0ODUxMzYyOTkzOTcxMjA=","rest_id":"740485136299397120","affiliates_highlighted_label":{},"has_nft_avatar":false,"legacy":{"blocked_by":false,"blocking":false,"can_dm":true,"can_media_tag":false,"created_at":"Wed Jun 08 10:06:28 +0000 2016","default_profile":true,"default_profile_image":false,"description":"R-18。お絵描きお勉強中っす。お題箱(https://t.co/BE9pJR7XmD) skeb (https://t.co/WTOHnDq1OJ)最後の扉(@gear_sankakukin)","entities":{"description":{"urls":[{"display_url":"odaibako.net/u/sankaku_gear","expanded_url":"http://odaibako.net/u/sankaku_gear","url":"https://t.co/BE9pJR7XmD","indices":[20,43]},{"display_url":"skeb.jp/@sankaku_gear","expanded_url":"http://skeb.jp/@sankaku_gear","url":"https://t.co/WTOHnDq1OJ","indices":[51,74]}]},"url":{"urls":[{"display_url":"pixiv.net/users/30556463","expanded_url":"https://www.pixiv.net/users/30556463","url":"https://t.co/4p3qturcrW","indices":[0,23]}]}},"fast_followers_count":0,"favourites_count":26154,"follow_request_sent":false,"followed_by":false,"followers_count":16020,"following":false,"friends_count":882,"has_custom_timelines":true,"is_translator":false,"listed_count":204,"location":"ウエスタンヘンプのループタイになりたい","media_count":1013,"muting":false,"name":"三角筋ギア","normal_followers_count":16020,"notifications":false,"pinned_tweet_ids_str":["1447581183248789504"],"possibly_sensitive":true,"profile_banner_extensions":{"mediaColor":{"r":{"ok":{"palette":[{"percentage":98.58,"rgb":{"blue":0,"green":0,"red":0}},{"percentage":1.42,"rgb":{"blue":111,"green":111,"red":111}}]}}}},"profile_banner_url":"https://pbs.twimg.com/profile_banners/740485136299397120/1588761569","profile_image_extensions":{"mediaColor":{"r":{"ok":{"palette":[{"percentage":44.38,"rgb":{"blue":200,"green":233,"red":253}},{"percentage":39.56,"rgb":{"blue":74,"green":73,"red":82}},{"percentage":5.94,"rgb":{"blue":124,"green":128,"red":149}},{"percentage":2.87,"rgb":{"blue":173,"green":159,"red":161}},{"percentage":0.81,"rgb":{"blue":165,"green":107,"red":83}}]}}}},"profile_image_url_https":"https://pbs.twimg.com/profile_images/1469638385903886337/NVjQ14zU_normal.jpg","profile_interstitial_type":"","protected":false,"screen_name":"sankaku_gear","statuses_count":20814,"translator_type":"none","url":"https://t.co/4p3qturcrW","verified":false,"want_retweets":false,"withheld_in_countries":[]},"super_follow_eligible":false,"super_followed_by":false,"super_following":false}}},"unmention_info":{},"legacy":{"created_at":"Mon May 30 23:14:30 +0000 2022","conversation_id_str":"1531413773524684801","display_text_range":[0,4],"entities":{"media":[{"display_url":"pic.twitter.com/zyW9bCy4hi","expanded_url":"https://twitter.com/sankaku_gear/status/1531413773524684801/photo/1","id_str":"1531413769330384896","indices":[5,28],"media_url_https":"https://pbs.twimg.com/media/FUCstZ0UYAARuSx.jpg","type":"photo","url":"https://t.co/zyW9bCy4hi","features":{"large":{"faces":[]},"medium":{"faces":[]},"small":{"faces":[]},"orig":{"faces":[]}},"sizes":{"large":{"h":1080,"w":766,"resize":"fit"},"medium":{"h":1080,"w":766,"resize":"fit"},"small":{"h":680,"w":482,"resize":"fit"},"thumb":{"h":150,"w":150,"resize":"crop"}},"original_info":{"height":1080,"width":766,"focus_rects":[{"x":0,"y":28,"w":766,"h":429},{"x":0,"y":0,"w":766,"h":766},{"x":0,"y":0,"w":766,"h":873},{"x":188,"y":0,"w":540,"h":1080},{"x":0,"y":0,"w":766,"h":1080}]}}],"user_mentions":[],"urls":[],"hashtags":[],"symbols":[]},"extended_entities":{"media":[{"display_url":"pic.twitter.com/zyW9bCy4hi","expanded_url":"https://twitter.com/sankaku_gear/status/1531413773524684801/photo/1","id_str":"1531413769330384896","indices":[5,28],"media_key":"3_1531413769330384896","media_url_https":"https://pbs.twimg.com/media/FUCstZ0UYAARuSx.jpg","type":"photo","url":"https://t.co/zyW9bCy4hi","ext_media_color":{"palette":[{"percentage":59.62,"rgb":{"blue":255,"green":254,"red":255}},{"percentage":25.23,"rgb":{"blue":83,"green":88,"red":98}},{"percentage":9.39,"rgb":{"blue":195,"green":157,"red":140}},{"percentage":1.38,"rgb":{"blue":133,"green":148,"red":187}},{"percentage":0.73,"rgb":{"blue":78,"green":95,"red":119}}]},"ext_media_availability":{"status":"Available"},"features":{"large":{"faces":[]},"medium":{"faces":[]},"small":{"faces":[]},"orig":{"faces":[]}},"sizes":{"large":{"h":1080,"w":766,"resize":"fit"},"medium":{"h":1080,"w":766,"resize":"fit"},"small":{"h":680,"w":482,"resize":"fit"},"thumb":{"h":150,"w":150,"resize":"crop"}},"original_info":{"height":1080,"width":766,"focus_rects":[{"x":0,"y":28,"w":766,"h":429},{"x":0,"y":0,"w":766,"h":766},{"x":0,"y":0,"w":766,"h":873},{"x":188,"y":0,"w":540,"h":1080},{"x":0,"y":0,"w":766,"h":1080}]}}]},"favorite_count":1152,"favorited":false,"full_text":"ゆみさん https://t.co/zyW9bCy4hi","is_quote_status":false,"lang":"ja","possibly_sensitive":true,"possibly_sensitive_editable":true,"quote_count":0,"reply_count":14,"retweet_count":351,"retweeted":false,"source":"<a href=\"http://twitter.com/download/iphone\" rel=\"nofollow\">Twitter for iPhone</a>","user_id_str":"740485136299397120","id_str":"1531413773524684801","self_thread":{"id_str":"1531413773524684801"}}}},"tweetDisplayType":"Tweet"}}},{"entryId":"tweet-1531317715595538432","sortIndex":"433577716758895360","content":{"entryType":"TimelineTimelineItem","itemContent":{"itemType":"TimelineTweet","tweet_results":{"result":{"__typename":"Tweet","rest_id":"1531317715595538432","core":{"user_results":{"result":{"__typename":"User","id":"VXNlcjoxMjg1MDM5NjkwMzI4ODg3Mjk2","rest_id":"1285039690328887296","affiliates_highlighted_label":{},"has_nft_avatar":false,"legacy":{"blocked_by":false,"blocking":false,"can_dm":false,"can_media_tag":true,"created_at":"Mon Jul 20 02:32:00 +0000 2020","default_profile":true,"default_profile_image":false,"description":"Contact \uD83D\uDC8C 837007108@qq.com\nhttps://t.co/EEo66iEc3K","entities":{"description":{"urls":[{"display_url":"pixiv.net/users/10665173","expanded_url":"https://www.pixiv.net/users/10665173","url":"https://t.co/EEo66iEc3K","indices":[27,50]}]}},"fast_followers_count":0,"favourites_count":59,"follow_request_sent":false,"followed_by":false,"followers_count":13465,"following":false,"friends_count":93,"has_custom_timelines":true,"is_translator":false,"listed_count":165,"location":"","media_count":16,"muting":false,"name":"三十壹","normal_followers_count":13465,"notifications":false,"pinned_tweet_ids_str":["1530076363041886208"],"possibly_sensitive":false,"profile_banner_extensions":{"mediaColor":{"r":{"ok":{"palette":[{"percentage":45.88,"rgb":{"blue":55,"green":54,"red":65}},{"percentage":13.77,"rgb":{"blue":170,"green":186,"red":210}},{"percentage":11.5,"rgb":{"blue":95,"green":133,"red":170}},{"percentage":8.47,"rgb":{"blue":42,"green":38,"red":165}},{"percentage":3.36,"rgb":{"blue":59,"green":58,"red":125}}]}}}},"profile_banner_url":"https://pbs.twimg.com/profile_banners/1285039690328887296/1650883338","profile_image_extensions":{"mediaColor":{"r":{"ok":{"palette":[{"percentage":89.83,"rgb":{"blue":228,"green":234,"red":244}},{"percentage":9.14,"rgb":{"blue":109,"green":110,"red":118}},{"percentage":0.56,"rgb":{"blue":53,"green":55,"red":62}},{"percentage":0.14,"rgb":{"blue":81,"green":90,"red":189}}]}}}},"profile_image_url_https":"https://pbs.twimg.com/profile_images/1518540648344743937/RcBT_xaD_normal.jpg","profile_interstitial_type":"","protected":false,"screen_name":"General65168880","statuses_count":24,"translator_type":"none","verified":false,"want_retweets":false,"withheld_in_countries":[]},"super_follow_eligible":false,"super_followed_by":false,"super_following":false}}},"unmention_info":{},"legacy":{"created_at":"Mon May 30 16:52:48 +0000 2022","conversation_id_str":"1531317715595538432","display_text_range":[0,39],"entities":{"media":[{"display_url":"pic.twitter.com/AGxzrCpaaF","expanded_url":"https://twitter.com/General65168880/status/1531317715595538432/photo/1","id_str":"1531317188593786881","indices":[40,63],"media_url_https":"https://pbs.twimg.com/media/FUBU3qiVIAEBnRa.jpg","type":"photo","url":"https://t.co/AGxzrCpaaF","features":{"large":{"faces":[]},"medium":{"faces":[]},"small":{"faces":[]},"orig":{"faces":[]}},"sizes":{"large":{"h":2048,"w":1365,"resize":"fit"},"medium":{"h":1200,"w":800,"resize":"fit"},"small":{"h":680,"w":453,"resize":"fit"},"thumb":{"h":150,"w":150,"resize":"crop"}},"original_info":{"height":3000,"width":2000,"focus_rects":[{"x":0,"y":1880,"w":2000,"h":1120},{"x":0,"y":1000,"w":2000,"h":2000},{"x":0,"y":720,"w":2000,"h":2280},{"x":500,"y":0,"w":1500,"h":3000},{"x":0,"y":0,"w":2000,"h":3000}]}}],"user_mentions":[],"urls":[],"hashtags":[{"indices":[0,8],"text":"アズールレーン"},{"indices":[9,18],"text":"AzurLane"},{"indices":[19,24],"text":"碧蓝航线"}],"symbols":[]},"extended_entities":{"media":[{"display_url":"pic.twitter.com/AGxzrCpaaF","expanded_url":"https://twitter.com/General65168880/status/1531317715595538432/photo/1","id_str":"1531317188593786881","indices":[40,63],"media_key":"3_1531317188593786881","media_url_https":"https://pbs.twimg.com/media/FUBU3qiVIAEBnRa.jpg","type":"photo","url":"https://t.co/AGxzrCpaaF","ext_media_color":{"palette":[{"percentage":73.31,"rgb":{"blue":230,"green":233,"red":247}},{"percentage":20.69,"rgb":{"blue":92,"green":78,"red":78}},{"percentage":1.48,"rgb":{"blue":148,"green":135,"red":128}},{"percentage":0.35,"rgb":{"blue":206,"green":199,"red":190}},{"percentage":0.28,"rgb":{"blue":146,"green":159,"red":229}}]},"ext_media_availability":{"status":"Available"},"features":{"large":{"faces":[]},"medium":{"faces":[]},"small":{"faces":[]},"orig":{"faces":[]}},"sizes":{"large":{"h":2048,"w":1365,"resize":"fit"},"medium":{"h":1200,"w":800,"resize":"fit"},"small":{"h":680,"w":453,"resize":"fit"},"thumb":{"h":150,"w":150,"resize":"crop"}},"original_info":{"height":3000,"width":2000,"focus_rects":[{"x":0,"y":1880,"w":2000,"h":1120},{"x":0,"y":1000,"w":2000,"h":2000},{"x":0,"y":720,"w":2000,"h":2280},{"x":500,"y":0,"w":1500,"h":3000},{"x":0,"y":0,"w":2000,"h":3000}]}}]},"favorite_count":32688,"favorited":false,"full_text":"#アズールレーン #AzurLane #碧蓝航线 Reply to me~\uD83D\uDC8C\uD83D\uDC8C https://t.co/AGxzrCpaaF","is_quote_status":false,"lang":"en","possibly_sensitive":false,"possibly_sensitive_editable":true,"quote_count":12,"reply_count":29,"retweet_count":5148,"retweeted":true,"source":"<a href=\"https://mobile.twitter.com\" rel=\"nofollow\">Twitter Web App</a>","user_id_str":"1285039690328887296","id_str":"1531317715595538432"}}},"tweetDisplayType":"Tweet"}}},{"entryId":"tweet-1531408056789401600","sortIndex":"433577700035350528","content":{"entryType":"TimelineTimelineItem","itemContent":{"itemType":"TimelineTweet","tweet_results":{"result":{"__typename":"Tweet","rest_id":"1531408056789401600","core":{"user_results":{"result":{"__typename":"User","id":"VXNlcjozMjY4NzY4MDQ=","rest_id":"326876804","affiliates_highlighted_label":{},"has_nft_avatar":false,"legacy":{"blocked_by":false,"blocking":false,"can_dm":false,"can_media_tag":true,"created_at":"Thu Jun 30 16:48:20 +0000 2011","default_profile":true,"default_profile_image":false,"description":"お絵かきおじさん兼水戸ホーリーホックサポーターです。絵とサッカーのツイートを同時並行でヤリまくるので、絵orサッカーでフォローされる方はご注意ください。\n健全版:https://t.co/ZcgAOhx787\nPixiv:https://t.co/JBMunTiA0T","entities":{"description":{"urls":[{"display_url":"twitter.com/Fukuda_shuushi","expanded_url":"https://twitter.com/Fukuda_shuushi","url":"https://t.co/ZcgAOhx787","indices":[81,104]},{"display_url":"pixiv.net/users/106843","expanded_url":"http://pixiv.net/users/106843","url":"https://t.co/JBMunTiA0T","indices":[111,134]}]},"url":{"urls":[{"display_url":"pixiv.net/member.php?id=…","expanded_url":"http://www.pixiv.net/member.php?id=106843","url":"https://t.co/A9ellCsm9r","indices":[0,23]}]}},"fast_followers_count":0,"favourites_count":18241,"follow_request_sent":false,"followed_by":false,"followers_count":237777,"following":false,"friends_count":1195,"has_custom_timelines":true,"is_translator":false,"listed_count":2481,"location":"生まれは金沢、心は水戸、体は埼玉","media_count":1956,"muting":false,"name":"福田シュウシ","normal_followers_count":237777,"notifications":false,"pinned_tweet_ids_str":["1522882861363527680"],"possibly_sensitive":true,"profile_banner_extensions":{"mediaColor":{"r":{"ok":{"palette":[{"percentage":40.61,"rgb":{"blue":184,"green":198,"red":237}},{"percentage":27.14,"rgb":{"blue":63,"green":62,"red":104}},{"percentage":8.12,"rgb":{"blue":104,"green":115,"red":181}},{"percentage":2.6,"rgb":{"blue":41,"green":34,"red":40}},{"percentage":1.45,"rgb":{"blue":234,"green":253,"red":255}}]}}}},"profile_banner_url":"https://pbs.twimg.com/profile_banners/326876804/1637939115","profile_image_extensions":{"mediaColor":{"r":{"ok":{"palette":[{"percentage":39.86,"rgb":{"blue":165,"green":173,"red":240}},{"percentage":30.0,"rgb":{"blue":75,"green":76,"red":133}},{"percentage":7.92,"rgb":{"blue":251,"green":253,"red":253}},{"percentage":5.6,"rgb":{"blue":113,"green":112,"red":194}},{"percentage":3.03,"rgb":{"blue":70,"green":30,"red":41}}]}}}},"profile_image_url_https":"https://pbs.twimg.com/profile_images/1426679569759707136/NtyZ2Q0p_normal.jpg","profile_interstitial_type":"sensitive_media","protected":false,"screen_name":"Fukuda_shushi","statuses_count":97296,"translator_type":"none","url":"https://t.co/A9ellCsm9r","verified":false,"want_retweets":false,"withheld_in_countries":[]},"super_follow_eligible":false,"super_followed_by":false,"super_following":false}}},"unmention_info":{},"legacy":{"created_at":"Mon May 30 22:51:47 +0000 2022","conversation_id_str":"1531408056789401600","display_text_range":[0,8],"entities":{"media":[{"display_url":"pic.twitter.com/E60CORiBVy","expanded_url":"https://twitter.com/Fukuda_shushi/status/1531408056789401600/photo/1","id_str":"1531407939894149121","indices":[9,32],"media_url_https":"https://pbs.twimg.com/media/FUCnaFeagAELtYe.jpg","type":"photo","url":"https://t.co/E60CORiBVy","features":{"large":{"faces":[]},"medium":{"faces":[]},"small":{"faces":[]},"orig":{"faces":[]}},"sizes":{"large":{"h":2048,"w":1468,"resize":"fit"},"medium":{"h":1200,"w":860,"resize":"fit"},"small":{"h":680,"w":487,"resize":"fit"},"thumb":{"h":150,"w":150,"resize":"crop"}},"original_info":{"height":3000,"width":2150,"focus_rects":[{"x":0,"y":1273,"w":2150,"h":1204},{"x":0,"y":800,"w":2150,"h":2150},{"x":0,"y":549,"w":2150,"h":2451},{"x":375,"y":0,"w":1500,"h":3000},{"x":0,"y":0,"w":2150,"h":3000}]}}],"user_mentions":[],"urls":[],"hashtags":[],"symbols":[]},"extended_entities":{"media":[{"display_url":"pic.twitter.com/E60CORiBVy","expanded_url":"https://twitter.com/Fukuda_shushi/status/1531408056789401600/photo/1","id_str":"1531407939894149121","indices":[9,32],"media_key":"3_1531407939894149121","media_url_https":"https://pbs.twimg.com/media/FUCnaFeagAELtYe.jpg","type":"photo","url":"https://t.co/E60CORiBVy","ext_media_color":{"palette":[{"percentage":55.2,"rgb":{"blue":209,"green":220,"red":249}},{"percentage":20.31,"rgb":{"blue":53,"green":44,"red":59}},{"percentage":8.96,"rgb":{"blue":207,"green":186,"red":202}},{"percentage":2.53,"rgb":{"blue":138,"green":138,"red":207}},{"percentage":1.13,"rgb":{"blue":74,"green":63,"red":123}}]},"ext_media_availability":{"status":"Available"},"features":{"large":{"faces":[]},"medium":{"faces":[]},"small":{"faces":[]},"orig":{"faces":[]}},"sizes":{"large":{"h":2048,"w":1468,"resize":"fit"},"medium":{"h":1200,"w":860,"resize":"fit"},"small":{"h":680,"w":487,"resize":"fit"},"thumb":{"h":150,"w":150,"resize":"crop"}},"original_info":{"height":3000,"width":2150,"focus_rects":[{"x":0,"y":1273,"w":2150,"h":1204},{"x":0,"y":800,"w":2150,"h":2150},{"x":0,"y":549,"w":2150,"h":2451},{"x":375,"y":0,"w":1500,"h":3000},{"x":0,"y":0,"w":2150,"h":3000}]}}]},"favorite_count":8842,"favorited":false,"full_text":"プリンツオイゲン https://t.co/E60CORiBVy","is_quote_status":false,"lang":"ja","possibly_sensitive":true,"possibly_sensitive_editable":false,"quote_count":5,"reply_count":54,"retweet_count":1629,"retweeted":false,"source":"<a href=\"https://mobile.twitter.com\" rel=\"nofollow\">Twitter Web App</a>","user_id_str":"326876804","id_str":"1531408056789401600"}}},"tweetDisplayType":"Tweet"}}},{"entryId":"tweet-1531208796441235456","sortIndex":"433561742321828864","content":{"entryType":"TimelineTimelineItem","itemContent":{"itemType":"TimelineTweet","tweet_results":{},"tweetDisplayType":"Tweet"}}},{"entryId":"tweet-1531212030023462912","sortIndex":"433561608317691648","content":{"entryType":"TimelineTimelineItem","itemContent":{"itemType":"TimelineTweet","tweet_results":{"result":{"__typename":"Tweet","rest_id":"1531212030023462912","core":{"user_results":{"result":{"__typename":"User","id":"VXNlcjoyNzEzMDA5NTY=","rest_id":"271300956","affiliates_highlighted_label":{},"has_nft_avatar":false,"legacy":{"blocked_by":false,"blocking":false,"can_dm":false,"can_media_tag":false,"created_at":"Thu Mar 24 07:13:20 +0000 2011","default_profile":false,"default_profile_image":false,"description":"(EN) Business via email : sakonlieur@gmail.com \n⚠️Repost with CREDIT+link | pfp & personal wallp use its OK |\n\nQ&A HERE \uD83D\uDC49 https://t.co/R29GTFybfa \uD83D\uDC48","entities":{"description":{"urls":[{"display_url":"linktr.ee/sakonlieur","expanded_url":"http://linktr.ee/sakonlieur","url":"https://t.co/R29GTFybfa","indices":[122,145]}]},"url":{"urls":[{"display_url":"pixiv.net/en/users/13072…","expanded_url":"http://pixiv.net/en/users/13072125","url":"https://t.co/h79e9sYJTI","indices":[0,23]}]}},"fast_followers_count":0,"favourites_count":8604,"follow_request_sent":false,"followed_by":false,"followers_count":122844,"following":false,"friends_count":1110,"has_custom_timelines":true,"is_translator":false,"listed_count":597,"location":"check linktree for questions","media_count":1508,"muting":false,"name":"SAKON\uD83D\uDC33✨","normal_followers_count":122844,"notifications":false,"pinned_tweet_ids_str":["1355140501825933312"],"possibly_sensitive":false,"profile_banner_extensions":{"mediaColor":{"r":{"ok":{"palette":[{"percentage":46.98,"rgb":{"blue":249,"green":248,"red":236}},{"percentage":21.93,"rgb":{"blue":149,"green":111,"red":84}},{"percentage":13.43,"rgb":{"blue":53,"green":42,"red":52}},{"percentage":3.87,"rgb":{"blue":35,"green":49,"red":91}},{"percentage":3.72,"rgb":{"blue":215,"green":170,"red":112}}]}}}},"profile_banner_url":"https://pbs.twimg.com/profile_banners/271300956/1639304685","profile_image_extensions":{"mediaColor":{"r":{"ok":{"palette":[{"percentage":67.5,"rgb":{"blue":220,"green":228,"red":235}},{"percentage":25.9,"rgb":{"blue":39,"green":36,"red":47}},{"percentage":7.95,"rgb":{"blue":107,"green":106,"red":123}},{"percentage":0.26,"rgb":{"blue":40,"green":62,"red":83}},{"percentage":0.12,"rgb":{"blue":98,"green":90,"red":121}}]}}}},"profile_image_url_https":"https://pbs.twimg.com/profile_images/1381603584844853257/J3sZiKCg_normal.jpg","profile_interstitial_type":"","protected":false,"screen_name":"sakonlieur","statuses_count":13085,"translator_type":"none","url":"https://t.co/h79e9sYJTI","verified":false,"want_retweets":false,"withheld_in_countries":[]},"super_follow_eligible":false,"super_followed_by":false,"super_following":false}}},"unmention_info":{},"legacy":{"created_at":"Mon May 30 09:52:51 +0000 2022","conversation_id_str":"1531212030023462912","display_text_range":[0,26],"entities":{"media":[{"display_url":"pic.twitter.com/l6fu9SLzXf","expanded_url":"https://twitter.com/sakonlieur/status/1531212030023462912/photo/1","id_str":"1531211873882079233","indices":[27,50],"media_url_https":"https://pbs.twimg.com/media/FT_1FiqaAAEWHwZ.jpg","type":"photo","url":"https://t.co/l6fu9SLzXf","features":{"large":{"faces":[]},"medium":{"faces":[]},"small":{"faces":[]},"orig":{"faces":[]}},"sizes":{"large":{"h":2048,"w":946,"resize":"fit"},"medium":{"h":1200,"w":554,"resize":"fit"},"small":{"h":680,"w":314,"resize":"fit"},"thumb":{"h":150,"w":150,"resize":"crop"}},"original_info":{"height":2598,"width":1200,"focus_rects":[{"x":0,"y":118,"w":1200,"h":672},{"x":0,"y":0,"w":1200,"h":1200},{"x":0,"y":0,"w":1200,"h":1368},{"x":0,"y":0,"w":1200,"h":2400},{"x":0,"y":0,"w":1200,"h":2598}]}}],"user_mentions":[],"urls":[],"hashtags":[{"indices":[4,7],"text":"原神"},{"indices":[8,15],"text":"childe"},{"indices":[16,26],"text":"tartaglia"}],"symbols":[]},"extended_entities":{"media":[{"display_url":"pic.twitter.com/l6fu9SLzXf","expanded_url":"https://twitter.com/sakonlieur/status/1531212030023462912/photo/1","id_str":"1531211873882079233","indices":[27,50],"media_key":"3_1531211873882079233","media_url_https":"https://pbs.twimg.com/media/FT_1FiqaAAEWHwZ.jpg","type":"photo","url":"https://t.co/l6fu9SLzXf","ext_media_color":{"palette":[{"percentage":38.41,"rgb":{"blue":243,"green":178,"red":107}},{"percentage":30.24,"rgb":{"blue":90,"green":49,"red":38}},{"percentage":11.2,"rgb":{"blue":229,"green":209,"red":155}},{"percentage":9.18,"rgb":{"blue":154,"green":127,"red":128}},{"percentage":2.99,"rgb":{"blue":80,"green":65,"red":74}}]},"ext_media_availability":{"status":"Available"},"features":{"large":{"faces":[]},"medium":{"faces":[]},"small":{"faces":[]},"orig":{"faces":[]}},"sizes":{"large":{"h":2048,"w":946,"resize":"fit"},"medium":{"h":1200,"w":554,"resize":"fit"},"small":{"h":680,"w":314,"resize":"fit"},"thumb":{"h":150,"w":150,"resize":"crop"}},"original_info":{"height":2598,"width":1200,"focus_rects":[{"x":0,"y":118,"w":1200,"h":672},{"x":0,"y":0,"w":1200,"h":1200},{"x":0,"y":0,"w":1200,"h":1368},{"x":0,"y":0,"w":1200,"h":2400},{"x":0,"y":0,"w":1200,"h":2598}]}}]},"favorite_count":36631,"favorited":false,"full_text":"\uD83C\uDF0A\uD83E\uDEE7\n\n#原神 #childe #tartaglia https://t.co/l6fu9SLzXf","is_quote_status":false,"lang":"und","possibly_sensitive":false,"possibly_sensitive_editable":true,"quote_count":41,"reply_count":36,"retweet_count":5663,"retweeted":true,"source":"<a href=\"https://mobile.twitter.com\" rel=\"nofollow\">Twitter Web App</a>","user_id_str":"271300956","id_str":"1531212030023462912","self_thread":{"id_str":"1531212030023462912"}}}},"tweetDisplayType":"Tweet"}}},{"entryId":"tweet-1530739140312330240","sortIndex":"433560854385206784","content":{"entryType":"TimelineTimelineItem","itemContent":{"itemType":"TimelineTweet","tweet_results":{"result":{"__typename":"Tweet","rest_id":"1530739140312330240","core":{"user_results":{"result":{"__typename":"User","id":"VXNlcjoyNTAyNDU4Mzc=","rest_id":"250245837","affiliates_highlighted_label":{},"has_nft_avatar":false,"legacy":{"blocked_by":false,"blocking":false,"can_dm":true,"can_media_tag":true,"created_at":"Thu Feb 10 18:20:43 +0000 2011","default_profile":true,"default_profile_image":false,"description":"イラストレーターをやってます。お仕事募集中です。 ご相談はこちらから→howaitokyatto@hotmail.com ■fanbox→https://t.co/P7O25cUYaV ■pixiv→https://t.co/MPQE78wltp ■skeb→https://t.co/TsIxbvaMT5","entities":{"description":{"urls":[{"display_url":"yapo.fanbox.cc","expanded_url":"http://yapo.fanbox.cc","url":"https://t.co/P7O25cUYaV","indices":[69,92]},{"display_url":"pixiv.me/yaponishi","expanded_url":"http://pixiv.me/yaponishi","url":"https://t.co/MPQE78wltp","indices":[100,123]},{"display_url":"skeb.jp/@yaponishi","expanded_url":"http://skeb.jp/@yaponishi","url":"https://t.co/TsIxbvaMT5","indices":[130,153]}]},"url":{"urls":[{"display_url":"harataira.net/~yapo/index.ht…","expanded_url":"http://harataira.net/~yapo/index.html","url":"https://t.co/rYjtP0bb8P","indices":[0,23]}]}},"fast_followers_count":0,"favourites_count":15171,"follow_request_sent":false,"followed_by":false,"followers_count":246025,"following":false,"friends_count":526,"has_custom_timelines":true,"is_translator":false,"listed_count":2517,"location":"地球","media_count":1342,"muting":false,"name":"yapo","normal_followers_count":246025,"notifications":false,"pinned_tweet_ids_str":["1488389716383010817"],"possibly_sensitive":false,"profile_banner_extensions":{"mediaColor":{"r":{"ok":{"palette":[{"percentage":54.67,"rgb":{"blue":231,"green":240,"red":254}},{"percentage":24.31,"rgb":{"blue":143,"green":187,"red":229}},{"percentage":8.59,"rgb":{"blue":157,"green":164,"red":233}},{"percentage":4.12,"rgb":{"blue":47,"green":54,"red":97}},{"percentage":0.96,"rgb":{"blue":182,"green":233,"red":249}}]}}}},"profile_banner_url":"https://pbs.twimg.com/profile_banners/250245837/1649801828","profile_image_extensions":{"mediaColor":{"r":{"ok":{"palette":[{"percentage":93.65,"rgb":{"blue":218,"green":218,"red":218}},{"percentage":5.1,"rgb":{"blue":13,"green":13,"red":13}}]}}}},"profile_image_url_https":"https://pbs.twimg.com/profile_images/1509566784961413120/XD6K3zW__normal.jpg","profile_interstitial_type":"","protected":false,"screen_name":"yaponishi","statuses_count":85795,"translator_type":"none","url":"https://t.co/rYjtP0bb8P","verified":false,"want_retweets":false,"withheld_in_countries":[]},"professional":{"rest_id":"1455867035083177990","professional_type":"Creator","category":[]},"super_follow_eligible":false,"super_followed_by":false,"super_following":false}}},"unmention_info":{},"legacy":{"created_at":"Sun May 29 02:33:45 +0000 2022","conversation_id_str":"1530739140312330240","display_text_range":[0,34],"entities":{"media":[{"display_url":"pic.twitter.com/EqAhZvN0Tm","expanded_url":"https://twitter.com/yaponishi/status/1530739140312330240/photo/1","id_str":"1530738471698313219","indices":[35,58],"media_url_https":"https://pbs.twimg.com/media/FT5Gh6GaMAMeBN9.jpg","type":"photo","url":"https://t.co/EqAhZvN0Tm","features":{"large":{"faces":[{"x":314,"y":275,"h":240,"w":240}]},"medium":{"faces":[{"x":314,"y":275,"h":240,"w":240}]},"small":{"faces":[{"x":178,"y":155,"h":136,"w":136}]},"orig":{"faces":[{"x":314,"y":275,"h":240,"w":240}]}},"sizes":{"large":{"h":1200,"w":848,"resize":"fit"},"medium":{"h":1200,"w":848,"resize":"fit"},"small":{"h":680,"w":481,"resize":"fit"},"thumb":{"h":150,"w":150,"resize":"crop"}},"original_info":{"height":1200,"width":848,"focus_rects":[{"x":0,"y":0,"w":848,"h":475},{"x":0,"y":0,"w":848,"h":848},{"x":0,"y":0,"w":848,"h":967},{"x":0,"y":0,"w":600,"h":1200},{"x":0,"y":0,"w":848,"h":1200}]}}],"user_mentions":[],"urls":[],"hashtags":[],"symbols":[]},"extended_entities":{"media":[{"display_url":"pic.twitter.com/EqAhZvN0Tm","expanded_url":"https://twitter.com/yaponishi/status/1530739140312330240/photo/1","id_str":"1530738471698313219","indices":[35,58],"media_key":"3_1530738471698313219","media_url_https":"https://pbs.twimg.com/media/FT5Gh6GaMAMeBN9.jpg","type":"photo","url":"https://t.co/EqAhZvN0Tm","ext_media_color":{"palette":[{"percentage":48.05,"rgb":{"blue":219,"green":208,"red":212}},{"percentage":22.38,"rgb":{"blue":40,"green":35,"red":44}},{"percentage":11.39,"rgb":{"blue":161,"green":114,"red":110}},{"percentage":1.35,"rgb":{"blue":174,"green":184,"red":236}},{"percentage":1.06,"rgb":{"blue":214,"green":182,"red":147}}]},"ext_media_availability":{"status":"Available"},"features":{"large":{"faces":[{"x":314,"y":275,"h":240,"w":240}]},"medium":{"faces":[{"x":314,"y":275,"h":240,"w":240}]},"small":{"faces":[{"x":178,"y":155,"h":136,"w":136}]},"orig":{"faces":[{"x":314,"y":275,"h":240,"w":240}]}},"sizes":{"large":{"h":1200,"w":848,"resize":"fit"},"medium":{"h":1200,"w":848,"resize":"fit"},"small":{"h":680,"w":481,"resize":"fit"},"thumb":{"h":150,"w":150,"resize":"crop"}},"original_info":{"height":1200,"width":848,"focus_rects":[{"x":0,"y":0,"w":848,"h":475},{"x":0,"y":0,"w":848,"h":848},{"x":0,"y":0,"w":848,"h":967},{"x":0,"y":0,"w":600,"h":1200},{"x":0,"y":0,"w":848,"h":1200}]}}]},"favorite_count":9889,"favorited":false,"full_text":"自室に招いた先生が寝てしまい、寝顔を見てたら朝を迎えてしまったヒナ。 https://t.co/EqAhZvN0Tm","is_quote_status":false,"lang":"ja","possibly_sensitive":false,"possibly_sensitive_editable":true,"quote_count":0,"reply_count":15,"retweet_count":2299,"retweeted":true,"source":"<a href=\"https://mobile.twitter.com\" rel=\"nofollow\">Twitter Web App</a>","user_id_str":"250245837","id_str":"1530739140312330240"}}},"tweetDisplayType":"Tweet"}}},{"entryId":"tweet-1530833709586591744","sortIndex":"433560850931744768","content":{"entryType":"TimelineTimelineItem","itemContent":{"itemType":"TimelineTweet","tweet_results":{"result":{"__typename":"Tweet","rest_id":"1530833709586591744","core":{"user_results":{"result":{"__typename":"User","id":"VXNlcjoxNDMzMjg2MDIyMjU5ODk2MzI1","rest_id":"1433286022259896325","affiliates_highlighted_label":{},"has_nft_avatar":false,"legacy":{"blocked_by":false,"blocking":false,"can_dm":false,"can_media_tag":true,"created_at":"Thu Sep 02 04:30:07 +0000 2021","default_profile":true,"default_profile_image":false,"description":"ブルアカとかの絵を描きます pixiv / https://t.co/NGMUNEr1K2 / https://t.co/WMuPdP5BA1 ←(オリキャラスタンプ作った)","entities":{"description":{"urls":[{"display_url":"pixiv.net/users/53718392","expanded_url":"https://www.pixiv.net/users/53718392","url":"https://t.co/NGMUNEr1K2","indices":[22,45]},{"display_url":"line.me/S/sticker/1861…","expanded_url":"https://line.me/S/sticker/18617207","url":"https://t.co/WMuPdP5BA1","indices":[48,71]}]}},"fast_followers_count":0,"favourites_count":5314,"follow_request_sent":false,"followed_by":false,"followers_count":6835,"following":false,"friends_count":165,"has_custom_timelines":true,"is_translator":false,"listed_count":83,"location":"","media_count":132,"muting":false,"name":"むてき","normal_followers_count":6835,"notifications":false,"pinned_tweet_ids_str":["1515712818456457218"],"possibly_sensitive":true,"profile_banner_extensions":{"mediaColor":{"r":{"ok":{"palette":[{"percentage":77.54,"rgb":{"blue":165,"green":133,"red":210}},{"percentage":12.92,"rgb":{"blue":103,"green":86,"red":112}},{"percentage":5.98,"rgb":{"blue":202,"green":186,"red":212}},{"percentage":1.34,"rgb":{"blue":72,"green":81,"red":137}},{"percentage":1.2,"rgb":{"blue":149,"green":115,"red":222}}]}}}},"profile_banner_url":"https://pbs.twimg.com/profile_banners/1433286022259896325/1632052266","profile_image_extensions":{"mediaColor":{"r":{"ok":{"palette":[{"percentage":68.85,"rgb":{"blue":246,"green":249,"red":254}},{"percentage":27.85,"rgb":{"blue":150,"green":137,"red":223}},{"percentage":2.26,"rgb":{"blue":124,"green":121,"red":143}},{"percentage":0.74,"rgb":{"blue":240,"green":185,"red":208}}]}}}},"profile_image_url_https":"https://pbs.twimg.com/profile_images/1438637508154167303/u_OCU89A_normal.jpg","profile_interstitial_type":"sensitive_media","protected":false,"screen_name":"tenncyo114514","statuses_count":2037,"translator_type":"none","verified":false,"want_retweets":false,"withheld_in_countries":[]},"super_follow_eligible":false,"super_followed_by":false,"super_following":false}}},"unmention_info":{},"legacy":{"created_at":"Sun May 29 08:49:32 +0000 2022","conversation_id_str":"1530833709586591744","display_text_range":[0,9],"entities":{"media":[{"display_url":"pic.twitter.com/KvTTyEARCP","expanded_url":"https://twitter.com/tenncyo114514/status/1530833709586591744/photo/1","id_str":"1530833704939307009","indices":[10,33],"media_url_https":"https://pbs.twimg.com/media/FT6dJNkaQAEs0M1.jpg","type":"photo","url":"https://t.co/KvTTyEARCP","features":{"large":{"faces":[{"x":664,"y":1134,"h":452,"w":452}]},"medium":{"faces":[{"x":388,"y":664,"h":264,"w":264}]},"small":{"faces":[{"x":220,"y":376,"h":150,"w":150}]},"orig":{"faces":[{"x":664,"y":1134,"h":452,"w":452}]}},"sizes":{"large":{"h":2048,"w":1318,"resize":"fit"},"medium":{"h":1200,"w":772,"resize":"fit"},"small":{"h":680,"w":438,"resize":"fit"},"thumb":{"h":150,"w":150,"resize":"crop"}},"original_info":{"height":2048,"width":1318,"focus_rects":[{"x":0,"y":603,"w":1318,"h":738},{"x":0,"y":313,"w":1318,"h":1318},{"x":0,"y":221,"w":1318,"h":1503},{"x":0,"y":0,"w":1024,"h":2048},{"x":0,"y":0,"w":1318,"h":2048}]}}],"user_mentions":[],"urls":[],"hashtags":[],"symbols":[]},"extended_entities":{"media":[{"display_url":"pic.twitter.com/KvTTyEARCP","expanded_url":"https://twitter.com/tenncyo114514/status/1530833709586591744/photo/1","id_str":"1530833704939307009","indices":[10,33],"media_key":"3_1530833704939307009","media_url_https":"https://pbs.twimg.com/media/FT6dJNkaQAEs0M1.jpg","type":"photo","url":"https://t.co/KvTTyEARCP","ext_media_color":{"palette":[{"percentage":83.53,"rgb":{"blue":255,"green":255,"red":255}},{"percentage":13.23,"rgb":{"blue":138,"green":124,"red":190}},{"percentage":2.15,"rgb":{"blue":118,"green":117,"red":118}},{"percentage":0.55,"rgb":{"blue":132,"green":186,"red":232}},{"percentage":0.34,"rgb":{"blue":241,"green":232,"red":210}}]},"ext_media_availability":{"status":"Available"},"features":{"large":{"faces":[{"x":664,"y":1134,"h":452,"w":452}]},"medium":{"faces":[{"x":388,"y":664,"h":264,"w":264}]},"small":{"faces":[{"x":220,"y":376,"h":150,"w":150}]},"orig":{"faces":[{"x":664,"y":1134,"h":452,"w":452}]}},"sizes":{"large":{"h":2048,"w":1318,"resize":"fit"},"medium":{"h":1200,"w":772,"resize":"fit"},"small":{"h":680,"w":438,"resize":"fit"},"thumb":{"h":150,"w":150,"resize":"crop"}},"original_info":{"height":2048,"width":1318,"focus_rects":[{"x":0,"y":603,"w":1318,"h":738},{"x":0,"y":313,"w":1318,"h":1318},{"x":0,"y":221,"w":1318,"h":1503},{"x":0,"y":0,"w":1024,"h":2048},{"x":0,"y":0,"w":1318,"h":2048}]}}]},"favorite_count":2483,"favorited":false,"full_text":"別垢であげてたユズ https://t.co/KvTTyEARCP","is_quote_status":false,"lang":"ja","possibly_sensitive":true,"possibly_sensitive_editable":false,"quote_count":0,"reply_count":4,"retweet_count":467,"retweeted":false,"source":"<a href=\"http://twitter.com/#!/download/ipad\" rel=\"nofollow\">Twitter for iPad</a>","user_id_str":"1433286022259896325","id_str":"1530833709586591744"}}},"tweetDisplayType":"Tweet"}}},{"entryId":"tweet-1531108145069559809","sortIndex":"433560840792256512","content":{"entryType":"TimelineTimelineItem","itemContent":{"itemType":"TimelineTweet","tweet_results":{"result":{"__typename":"Tweet","rest_id":"1531108145069559809","core":{"user_results":{"result":{"__typename":"User","id":"VXNlcjoxMTA1MDQ0NzE3Nzk5MDcxNzQ1","rest_id":"1105044717799071745","affiliates_highlighted_label":{},"has_nft_avatar":false,"legacy":{"blocked_by":false,"blocking":false,"can_dm":true,"can_media_tag":true,"created_at":"Mon Mar 11 09:56:06 +0000 2019","default_profile":false,"default_profile_image":false,"description":"駆け出しのフリーランスイラストレーターをしています。 既婚者。個人依頼も受け付けております。お仕事募集中です！ ご依頼はDMかこちらまで→soleil.mtfbwy03@gmail.com Skeb https://t.co/1Dxf8VFpnm","entities":{"description":{"urls":[{"display_url":"skeb.jp/@Soleilmtfbwy03","expanded_url":"http://skeb.jp/@Soleilmtfbwy03","url":"https://t.co/1Dxf8VFpnm","indices":[100,123]}]},"url":{"urls":[{"display_url":"pixiv.net/member.php?id=…","expanded_url":"https://www.pixiv.net/member.php?id=39049203","url":"https://t.co/Ra7qAD9h2y","indices":[0,23]}]}},"fast_followers_count":0,"favourites_count":209495,"follow_request_sent":false,"followed_by":false,"followers_count":19375,"following":false,"friends_count":263,"has_custom_timelines":true,"is_translator":false,"listed_count":317,"location":"君の瞳","media_count":515,"muting":false,"name":"鍛冶屋ソレイユ\uD83D\uDD28\uD83C\uDF3B/多忙につき低浮上","normal_followers_count":19375,"notifications":false,"pinned_tweet_ids_str":["1518425509373259777"],"possibly_sensitive":true,"profile_banner_extensions":{"mediaColor":{"r":{"ok":{"palette":[{"percentage":51.05,"rgb":{"blue":69,"green":75,"red":93}},{"percentage":34.94,"rgb":{"blue":162,"green":168,"red":187}},{"percentage":3.14,"rgb":{"blue":83,"green":98,"red":151}},{"percentage":1.11,"rgb":{"blue":104,"green":140,"red":172}},{"percentage":0.25,"rgb":{"blue":44,"green":70,"red":82}}]}}}},"profile_banner_url":"https://pbs.twimg.com/profile_banners/1105044717799071745/1649501762","profile_image_extensions":{"mediaColor":{"r":{"ok":{"palette":[{"percentage":47.9,"rgb":{"blue":46,"green":43,"red":43}},{"percentage":33.76,"rgb":{"blue":146,"green":153,"red":184}},{"percentage":2.76,"rgb":{"blue":87,"green":95,"red":140}},{"percentage":1.79,"rgb":{"blue":101,"green":97,"red":115}},{"percentage":0.24,"rgb":{"blue":113,"green":133,"red":204}}]}}}},"profile_image_url_https":"https://pbs.twimg.com/profile_images/1516953836786651136/jGW7TlwI_normal.jpg","profile_interstitial_type":"","protected":false,"screen_name":"Soleilmtfbwy03","statuses_count":21088,"translator_type":"none","url":"https://t.co/Ra7qAD9h2y","verified":false,"want_retweets":false,"withheld_in_countries":[]},"super_follow_eligible":false,"super_followed_by":false,"super_following":false}}},"unmention_info":{},"legacy":{"created_at":"Mon May 30 03:00:03 +0000 2022","conversation_id_str":"1531108145069559809","display_text_range":[0,1],"entities":{"media":[{"display_url":"pic.twitter.com/ssVoNHZYM5","expanded_url":"https://twitter.com/Soleilmtfbwy03/status/1531108145069559809/photo/1","id_str":"1531107466661879809","indices":[2,25],"media_url_https":"https://pbs.twimg.com/media/FT-WIPdUYAEkFtN.jpg","type":"photo","url":"https://t.co/ssVoNHZYM5","features":{"large":{"faces":[]},"medium":{"faces":[]},"small":{"faces":[]},"orig":{"faces":[]}},"sizes":{"large":{"h":2048,"w":1152,"resize":"fit"},"medium":{"h":1200,"w":675,"resize":"fit"},"small":{"h":680,"w":383,"resize":"fit"},"thumb":{"h":150,"w":150,"resize":"crop"}},"original_info":{"height":3840,"width":2160,"focus_rects":[{"x":0,"y":67,"w":2160,"h":1210},{"x":0,"y":0,"w":2160,"h":2160},{"x":0,"y":0,"w":2160,"h":2462},{"x":240,"y":0,"w":1920,"h":3840},{"x":0,"y":0,"w":2160,"h":3840}]}}],"user_mentions":[],"urls":[],"hashtags":[],"symbols":[]},"extended_entities":{"media":[{"display_url":"pic.twitter.com/ssVoNHZYM5","expanded_url":"https://twitter.com/Soleilmtfbwy03/status/1531108145069559809/photo/1","id_str":"1531107466661879809","indices":[2,25],"media_key":"3_1531107466661879809","media_url_https":"https://pbs.twimg.com/media/FT-WIPdUYAEkFtN.jpg","type":"photo","url":"https://t.co/ssVoNHZYM5","ext_media_color":{"palette":[{"percentage":66.91,"rgb":{"blue":124,"green":136,"red":163}},{"percentage":24.35,"rgb":{"blue":61,"green":64,"red":83}},{"percentage":4.29,"rgb":{"blue":209,"green":214,"red":225}},{"percentage":2.79,"rgb":{"blue":126,"green":137,"red":125}},{"percentage":1.0,"rgb":{"blue":169,"green":149,"red":172}}]},"ext_media_availability":{"status":"Available"},"features":{"large":{"faces":[]},"medium":{"faces":[]},"small":{"faces":[]},"orig":{"faces":[]}},"sizes":{"large":{"h":2048,"w":1152,"resize":"fit"},"medium":{"h":1200,"w":675,"resize":"fit"},"small":{"h":680,"w":383,"resize":"fit"},"thumb":{"h":150,"w":150,"resize":"crop"}},"original_info":{"height":3840,"width":2160,"focus_rects":[{"x":0,"y":67,"w":2160,"h":1210},{"x":0,"y":0,"w":2160,"h":2160},{"x":0,"y":0,"w":2160,"h":2462},{"x":240,"y":0,"w":1920,"h":3840},{"x":0,"y":0,"w":2160,"h":3840}]}}]},"favorite_count":2951,"favorited":false,"full_text":"\uD83C\uDF80 https://t.co/ssVoNHZYM5","is_quote_status":false,"lang":"und","possibly_sensitive":false,"possibly_sensitive_editable":true,"quote_count":0,"reply_count":11,"retweet_count":559,"retweeted":true,"source":"<a href=\"https://mobile.twitter.com\" rel=\"nofollow\">Twitter Web App</a>","user_id_str":"1105044717799071745","id_str":"1531108145069559809"}}},"tweetDisplayType":"Tweet"}}},{"entryId":"tweet-1531195670089986049","sortIndex":"433560119025037312","content":{"entryType":"TimelineTimelineItem","itemContent":{"itemType":"TimelineTweet","tweet_results":{"result":{"__typename":"Tweet","rest_id":"1531195670089986049","core":{"user_results":{"result":{"__typename":"User","id":"VXNlcjo1Njk2MzAyMDM=","rest_id":"569630203","affiliates_highlighted_label":{},"has_nft_avatar":false,"legacy":{"blocked_by":false,"blocking":false,"can_dm":true,"can_media_tag":false,"created_at":"Thu May 03 02:48:34 +0000 2012","default_profile":true,"default_profile_image":false,"description":"台湾のイラストレーター 今は日本語まだ勉強中\n\n■Fanboxとリクエスト→https://t.co/pTWSlip4RQ\n■PIXIV→https://t.co/i6JiGQfAep \n■お仕事 ご依頼等あれば【zaku2s640480@gmail.com】","entities":{"description":{"urls":[{"display_url":"whitebeara.fanbox.cc","expanded_url":"http://whitebeara.fanbox.cc","url":"https://t.co/pTWSlip4RQ","indices":[38,61]},{"display_url":"pixiv.net/users/357034","expanded_url":"https://www.pixiv.net/users/357034","url":"https://t.co/i6JiGQfAep","indices":[69,92]}]},"url":{"urls":[{"display_url":"pixiv.me/zaku2s","expanded_url":"http://pixiv.me/zaku2s","url":"https://t.co/U1ixODw3ep","indices":[0,23]}]}},"fast_followers_count":0,"favourites_count":35858,"follow_request_sent":false,"followed_by":false,"followers_count":62807,"following":true,"friends_count":2077,"has_custom_timelines":true,"is_translator":false,"listed_count":689,"location":"北極","media_count":1231,"muting":false,"name":"シロクマA＠リクエスト募集中","normal_followers_count":62807,"notifications":false,"pinned_tweet_ids_str":["1530824605471940609"],"possibly_sensitive":true,"profile_banner_extensions":{"mediaColor":{"r":{"ok":{"palette":[{"percentage":28.45,"rgb":{"blue":231,"green":192,"red":163}},{"percentage":21.15,"rgb":{"blue":71,"green":55,"red":38}},{"percentage":9.83,"rgb":{"blue":152,"green":177,"red":185}},{"percentage":9.81,"rgb":{"blue":34,"green":57,"red":50}},{"percentage":6.47,"rgb":{"blue":33,"green":110,"red":86}}]}}}},"profile_banner_url":"https://pbs.twimg.com/profile_banners/569630203/1538650485","profile_image_extensions":{"mediaColor":{"r":{"ok":{"palette":[{"percentage":58.34,"rgb":{"blue":159,"green":169,"red":181}},{"percentage":33.82,"rgb":{"blue":87,"green":80,"red":99}},{"percentage":3.08,"rgb":{"blue":103,"green":91,"red":76}},{"percentage":2.12,"rgb":{"blue":60,"green":52,"red":129}},{"percentage":0.95,"rgb":{"blue":29,"green":25,"red":35}}]}}}},"profile_image_url_https":"https://pbs.twimg.com/profile_images/1131137164358512640/94ZQG2yw_normal.png","profile_interstitial_type":"","protected":false,"screen_name":"Merufena","statuses_count":36522,"translator_type":"none","url":"https://t.co/U1ixODw3ep","verified":false,"want_retweets":true,"withheld_in_countries":[]},"super_follow_eligible":false,"super_followed_by":false,"super_following":false}}},"unmention_info":{},"legacy":{"created_at":"Mon May 30 08:47:50 +0000 2022","conversation_id_str":"1531195670089986049","display_text_range":[0,27],"entities":{"media":[{"display_url":"pic.twitter.com/b74qbp2zOW","expanded_url":"https://twitter.com/Merufena/status/1531195670089986049/photo/1","id_str":"1531195581267210240","indices":[28,51],"media_url_https":"https://pbs.twimg.com/media/FT_mRL8UcAALx1H.jpg","type":"photo","url":"https://t.co/b74qbp2zOW","features":{"large":{"faces":[]},"medium":{"faces":[]},"small":{"faces":[]},"orig":{"faces":[]}},"sizes":{"large":{"h":2000,"w":1351,"resize":"fit"},"medium":{"h":1200,"w":811,"resize":"fit"},"small":{"h":680,"w":459,"resize":"fit"},"thumb":{"h":150,"w":150,"resize":"crop"}},"original_info":{"height":2000,"width":1351,"focus_rects":[{"x":0,"y":0,"w":1351,"h":757},{"x":0,"y":0,"w":1351,"h":1351},{"x":0,"y":0,"w":1351,"h":1540},{"x":50,"y":0,"w":1000,"h":2000},{"x":0,"y":0,"w":1351,"h":2000}]}}],"user_mentions":[],"urls":[],"hashtags":[{"indices":[12,21],"text":"ブルーアーカイブ"},{"indices":[22,27],"text":"ブルアカ"}],"symbols":[]},"extended_entities":{"media":[{"display_url":"pic.twitter.com/b74qbp2zOW","expanded_url":"https://twitter.com/Merufena/status/1531195670089986049/photo/1","id_str":"1531195581267210240","indices":[28,51],"media_key":"3_1531195581267210240","media_url_https":"https://pbs.twimg.com/media/FT_mRL8UcAALx1H.jpg","type":"photo","url":"https://t.co/b74qbp2zOW","ext_media_color":{"palette":[{"percentage":71.84,"rgb":{"blue":222,"green":243,"red":252}},{"percentage":13.21,"rgb":{"blue":155,"green":118,"red":222}},{"percentage":9.76,"rgb":{"blue":94,"green":87,"red":92}},{"percentage":2.37,"rgb":{"blue":180,"green":168,"red":162}},{"percentage":0.54,"rgb":{"blue":250,"green":197,"red":106}}]},"ext_media_availability":{"status":"Available"},"features":{"large":{"faces":[]},"medium":{"faces":[]},"small":{"faces":[]},"orig":{"faces":[]}},"sizes":{"large":{"h":2000,"w":1351,"resize":"fit"},"medium":{"h":1200,"w":811,"resize":"fit"},"small":{"h":680,"w":459,"resize":"fit"},"thumb":{"h":150,"w":150,"resize":"crop"}},"original_info":{"height":2000,"width":1351,"focus_rects":[{"x":0,"y":0,"w":1351,"h":757},{"x":0,"y":0,"w":1351,"h":1351},{"x":0,"y":0,"w":1351,"h":1540},{"x":50,"y":0,"w":1000,"h":2000},{"x":0,"y":0,"w":1351,"h":2000}]}}]},"favorite_count":1931,"favorited":false,"full_text":"夏新刊ブルアカ本預定\n\n#ブルーアーカイブ\n#ブルアカ https://t.co/b74qbp2zOW","is_quote_status":false,"lang":"ja","possibly_sensitive":true,"possibly_sensitive_editable":false,"quote_count":0,"reply_count":3,"retweet_count":348,"retweeted":false,"source":"<a href=\"https://mobile.twitter.com\" rel=\"nofollow\">Twitter Web App</a>","user_id_str":"569630203","id_str":"1531195670089986049","self_thread":{"id_str":"1531195670089986049"}}}},"tweetDisplayType":"Tweet"}}},{"entryId":"tweet-1529760272675577856","sortIndex":"433560117716008704","content":{"entryType":"TimelineTimelineItem","itemContent":{"itemType":"TimelineTweet","tweet_results":{"result":{"__typename":"Tweet","rest_id":"1529760272675577856","core":{"user_results":{"result":{"__typename":"User","id":"VXNlcjoxMzUxMTk4OTA0MTA5NDU3NDEw","rest_id":"1351198904109457410","affiliates_highlighted_label":{},"has_nft_avatar":false,"legacy":{"blocked_by":false,"blocking":false,"can_dm":true,"can_media_tag":false,"created_at":"Mon Jan 18 16:05:14 +0000 2021","default_profile":true,"default_profile_image":false,"description":"漫画を描いたりイラストを描いたりする人です、二次創作多め（ブルアカ・アズレン）NSFW。(はぎわら えみりお) / Skeb：https://t.co/YfiWd2f57t / FANBOX：https://t.co/7Qb10XopWn","entities":{"description":{"urls":[{"display_url":"skeb.jp/@emirio110","expanded_url":"http://skeb.jp/@emirio110","url":"https://t.co/YfiWd2f57t","indices":[63,86]},{"display_url":"emirio110.fanbox.cc","expanded_url":"http://emirio110.fanbox.cc","url":"https://t.co/7Qb10XopWn","indices":[96,119]}]},"url":{"urls":[{"display_url":"pixiv.net/users/24420298","expanded_url":"https://www.pixiv.net/users/24420298","url":"https://t.co/1XKmrLDqrG","indices":[0,23]}]}},"fast_followers_count":0,"favourites_count":23748,"follow_request_sent":false,"followed_by":false,"followers_count":79882,"following":false,"friends_count":1343,"has_custom_timelines":false,"is_translator":false,"listed_count":767,"location":"","media_count":164,"muting":false,"name":"萩原エミリオ","normal_followers_count":79882,"notifications":false,"pinned_tweet_ids_str":["1448569135240077318"],"possibly_sensitive":true,"profile_banner_extensions":{"mediaColor":{"r":{"ok":{"palette":[{"percentage":40.23,"rgb":{"blue":181,"green":191,"red":225}},{"percentage":32.19,"rgb":{"blue":104,"green":119,"red":212}},{"percentage":15.7,"rgb":{"blue":65,"green":59,"red":83}},{"percentage":4.38,"rgb":{"blue":99,"green":115,"red":165}},{"percentage":1.02,"rgb":{"blue":159,"green":185,"red":226}}]}}}},"profile_banner_url":"https://pbs.twimg.com/profile_banners/1351198904109457410/1645396292","profile_image_extensions":{"mediaColor":{"r":{"ok":{"palette":[{"percentage":78.09,"rgb":{"blue":179,"green":190,"red":226}},{"percentage":9.42,"rgb":{"blue":80,"green":82,"red":170}},{"percentage":5.54,"rgb":{"blue":111,"green":126,"red":166}},{"percentage":1.5,"rgb":{"blue":233,"green":236,"red":141}},{"percentage":1.44,"rgb":{"blue":151,"green":168,"red":245}}]}}}},"profile_image_url_https":"https://pbs.twimg.com/profile_images/1524005871281315841/95D3udCA_normal.jpg","profile_interstitial_type":"sensitive_media","protected":false,"screen_name":"emirio110","statuses_count":13708,"translator_type":"none","url":"https://t.co/1XKmrLDqrG","verified":false,"want_retweets":false,"withheld_in_countries":[]},"super_follow_eligible":false,"super_followed_by":false,"super_following":false}}},"unmention_info":{},"legacy":{"created_at":"Thu May 26 09:44:05 +0000 2022","conversation_id_str":"1529760272675577856","display_text_range":[0,9],"entities":{"media":[{"display_url":"pic.twitter.com/8kEJ0tpbmO","expanded_url":"https://twitter.com/emirio110/status/1529760272675577856/photo/1","id_str":"1529760267927597056","indices":[10,33],"media_url_https":"https://pbs.twimg.com/media/FTrM29FUsAA--IA.jpg","type":"photo","url":"https://t.co/8kEJ0tpbmO","features":{"large":{"faces":[]},"medium":{"faces":[]},"small":{"faces":[]},"orig":{"faces":[]}},"sizes":{"large":{"h":838,"w":1227,"resize":"fit"},"medium":{"h":820,"w":1200,"resize":"fit"},"small":{"h":464,"w":680,"resize":"fit"},"thumb":{"h":150,"w":150,"resize":"crop"}},"original_info":{"height":838,"width":1227,"focus_rects":[{"x":0,"y":0,"w":1227,"h":687},{"x":346,"y":0,"w":838,"h":838},{"x":398,"y":0,"w":735,"h":838},{"x":556,"y":0,"w":419,"h":838},{"x":0,"y":0,"w":1227,"h":838}]}}],"user_mentions":[],"urls":[],"hashtags":[],"symbols":[]},"extended_entities":{"media":[{"display_url":"pic.twitter.com/8kEJ0tpbmO","expanded_url":"https://twitter.com/emirio110/status/1529760272675577856/photo/1","id_str":"1529760267927597056","indices":[10,33],"media_key":"3_1529760267927597056","media_url_https":"https://pbs.twimg.com/media/FTrM29FUsAA--IA.jpg","type":"photo","url":"https://t.co/8kEJ0tpbmO","ext_media_color":{"palette":[{"percentage":39.96,"rgb":{"blue":168,"green":187,"red":227}},{"percentage":35.38,"rgb":{"blue":40,"green":42,"red":50}},{"percentage":5.88,"rgb":{"blue":90,"green":44,"red":47}},{"percentage":4.21,"rgb":{"blue":141,"green":160,"red":225}},{"percentage":3.48,"rgb":{"blue":22,"green":24,"red":97}}]},"ext_media_availability":{"status":"Available"},"features":{"large":{"faces":[]},"medium":{"faces":[]},"small":{"faces":[]},"orig":{"faces":[]}},"sizes":{"large":{"h":838,"w":1227,"resize":"fit"},"medium":{"h":820,"w":1200,"resize":"fit"},"small":{"h":464,"w":680,"resize":"fit"},"thumb":{"h":150,"w":150,"resize":"crop"}},"original_info":{"height":838,"width":1227,"focus_rects":[{"x":0,"y":0,"w":1227,"h":687},{"x":346,"y":0,"w":838,"h":838},{"x":398,"y":0,"w":735,"h":838},{"x":556,"y":0,"w":419,"h":838},{"x":0,"y":0,"w":1227,"h":838}]}}]},"favorite_count":6311,"favorited":false,"full_text":"ハスミ緊縛 wip https://t.co/8kEJ0tpbmO","is_quote_status":false,"lang":"ja","possibly_sensitive":true,"possibly_sensitive_editable":false,"quote_count":4,"reply_count":14,"retweet_count":1006,"retweeted":false,"source":"<a href=\"http://twitter.com/#!/download/ipad\" rel=\"nofollow\">Twitter for iPad</a>","user_id_str":"1351198904109457410","id_str":"1529760272675577856"}}},"tweetDisplayType":"Tweet"}}},{"entryId":"cursor-top-433605062305826817","sortIndex":"433605062305826817","content":{"entryType":"TimelineTimelineCursor","value":"HCaAoOb4t+C8hAwAAA==","cursorType":"Top"}},{"entryId":"cursor-bottom-433560117716008703","sortIndex":"433560117716008703","content":{"entryType":"TimelineTimelineCursor","value":"HBaA/OnTqKiohAwAAA==","cursorType":"Bottom","stopOnEmptyResponse":true}}]}],"responseObjects":{"feedbackActions":[],"immediateReactions":[]}}}}}
