{"data":{"threaded_conversation_with_injections":{"instructions":[{"type":"TimelineAddEntries","entries":[{"entryId":"tweet-1426042768808284160","sortIndex":"7797329268046491647","content":{"entryType":"TimelineTimelineItem","itemContent":{"itemType":"TimelineTweet","tweet_results":{"result":{"__typename":"Tweet","rest_id":"1426042768808284160","core":{"user":{"id":"VXNlcjoyOTQyNDEyNA==","rest_id":"29424124","affiliates_highlighted_label":{},"legacy":{"blocked_by":false,"blocking":false,"can_dm":false,"can_media_tag":true,"created_at":"Tue Apr 07 10:45:21 +0000 2009","default_profile":true,"default_profile_image":false,"description":"サイエンスライターです。が、自分ではフィクション部分を限りなく小さくしたＳＦをやっているつもり。『ガメラ２ レギオン襲来』とか、『宇宙戦艦ヤマト２１９９』などのＳＦ考証もやらせていただきました。 『サはサイエンスのサ』という本を出してます。面白いから読んでね。（ ・∀・ ）","entities":{"description":{"urls":[]}},"fast_followers_count":0,"favourites_count":5202,"follow_request_sent":false,"followed_by":false,"followers_count":11630,"following":false,"friends_count":1706,"has_custom_timelines":true,"is_translator":false,"listed_count":922,"location":"神奈川","media_count":1844,"muting":false,"name":"しかのつかさ","normal_followers_count":11630,"notifications":false,"pinned_tweet_ids_str":[],"profile_banner_extensions":{"mediaColor":{"r":{"ok":{"palette":[{"percentage":85.88,"rgb":{"blue":176,"green":199,"red":226}},{"percentage":5.09,"rgb":{"blue":76,"green":111,"red":167}},{"percentage":4.23,"rgb":{"blue":58,"green":64,"red":70}},{"percentage":1.49,"rgb":{"blue":110,"green":161,"red":225}},{"percentage":1.25,"rgb":{"blue":241,"green":254,"red":255}}]}}}},"profile_banner_url":"https://pbs.twimg.com/profile_banners/29424124/1579045217","profile_image_extensions":{"mediaColor":{"r":{"ok":{"palette":[{"percentage":83.42,"rgb":{"blue":188,"green":204,"red":208}},{"percentage":11.1,"rgb":{"blue":75,"green":112,"red":158}},{"percentage":3.19,"rgb":{"blue":86,"green":99,"red":117}},{"percentage":1.73,"rgb":{"blue":97,"green":139,"red":185}},{"percentage":0.69,"rgb":{"blue":51,"green":51,"red":207}}]}}}},"profile_image_url_https":"https://pbs.twimg.com/profile_images/1121406306/sikasenbei_normal.jpg","profile_interstitial_type":"","protected":false,"screen_name":"sikano_tu","statuses_count":183174,"translator_type":"none","verified":false,"want_retweets":false,"withheld_in_countries":[]}}},"quoted_status_result":{"result":{"__typename":"Tweet","rest_id":"1425650239906533378","core":{"user":{"id":"VXNlcjoxNjQwNzE2MzM4","rest_id":"1640716338","affiliates_highlighted_label":{},"legacy":{"blocked_by":false,"blocking":false,"can_dm":false,"can_media_tag":false,"created_at":"Fri Aug 02 15:47:39 +0000 2013","default_profile":true,"default_profile_image":false,"description":"köttur(コッテル)はアイスランド語で“猫” つまり猫偏愛者。Sigur Rós/Coldplay/スピッツ/ミスチル好き。大宮サポですがミーヤと同じくらい愛媛の一平くんも尊敬 。psychiatrist/訳書 『愛着と精神療法』(星和書店)ほか (※個別相談にはリプしませんのでご理解下さい)※トプ画は川上浩一画伯","entities":{"description":{"urls":[]}},"fast_followers_count":0,"favourites_count":45085,"follow_request_sent":false,"followed_by":false,"followers_count":10174,"following":false,"friends_count":596,"has_custom_timelines":true,"is_translator":false,"listed_count":189,"location":"ツイートの無断転用、まとめを禁じます","media_count":3223,"muting":false,"name":"あつまるなköttur-lover22\uD83D\uDC31の森","normal_followers_count":10174,"notifications":false,"pinned_tweet_ids_str":["704651812222029824"],"profile_banner_extensions":{"mediaColor":{"r":{"ok":{"palette":[{"percentage":77.03,"rgb":{"blue":181,"green":185,"red":212}},{"percentage":12.86,"rgb":{"blue":163,"green":199,"red":245}},{"percentage":7.87,"rgb":{"blue":66,"green":54,"red":54}},{"percentage":0.74,"rgb":{"blue":178,"green":161,"red":176}},{"percentage":0.74,"rgb":{"blue":192,"green":211,"red":182}}]}}}},"profile_banner_url":"https://pbs.twimg.com/profile_banners/1640716338/1626532119","profile_image_extensions":{"mediaColor":{"r":{"ok":{"palette":[{"percentage":37.2,"rgb":{"blue":135,"green":155,"red":163}},{"percentage":24.8,"rgb":{"blue":50,"green":51,"red":56}},{"percentage":7.76,"rgb":{"blue":205,"green":193,"red":185}},{"percentage":4.97,"rgb":{"blue":56,"green":103,"red":24}},{"percentage":4.57,"rgb":{"blue":165,"green":223,"red":68}}]}}}},"profile_image_url_https":"https://pbs.twimg.com/profile_images/848021479543394305/Zl46uPX2_normal.jpg","profile_interstitial_type":"","protected":false,"screen_name":"kottur_lover22","statuses_count":416939,"translator_type":"none","verified":false,"want_retweets":false,"withheld_in_countries":[]}}},"legacy":{"created_at":"Thu Aug 12 02:47:59 +0000 2021","conversation_id_str":"1425650239906533378","display_text_range":[0,84],"entities":{"user_mentions":[],"urls":[],"hashtags":[],"symbols":[]},"favorite_count":4545,"favorited":false,"full_text":"はー。管轄保健所から、陽性者急増のため「濃厚接触者」検査は、\n①同居家族、\n②高齢者施設や障害者施設、病院\nに限定するとの通知ががが。\n\n残りは自助ですか。もうだめだ。","is_quote_status":false,"lang":"ja","quote_count":167,"reply_count":45,"retweet_count":3645,"retweeted":false,"source":"<a href=\"http://twitter.com/download/iphone\" rel=\"nofollow\">Twitter for iPhone</a>","user_id_str":"1640716338","id_str":"1425650239906533378"}}},"legacy":{"created_at":"Fri Aug 13 04:47:45 +0000 2021","conversation_id_str":"1426042768808284160","display_text_range":[0,58],"entities":{"user_mentions":[],"urls":[],"hashtags":[],"symbols":[]},"favorite_count":6,"favorited":false,"full_text":"つまり今後陽性者数が増えなくても、それは見落としてるだけで、増えてないわけではないということね。陽性率は上がるはず。","is_quote_status":true,"lang":"ja","quote_count":1,"quoted_status_id_str":"1425650239906533378","quoted_status_permalink":{"url":"https://t.co/oKfNYTbbWD","expanded":"https://twitter.com/kottur_lover22/status/1425650239906533378","display":"twitter.com/kottur_lover22…"},"reply_count":0,"retweet_count":11,"retweeted":false,"source":"<a href=\"http://twitter.com/#!/download/ipad\" rel=\"nofollow\">Twitter for iPad</a>","user_id_str":"29424124","id_str":"1426042768808284160"}}},"tweetDisplayType":"Tweet","hasModeratedReplies":false}}}]},{"type":"TimelineTerminateTimeline","direction":"Top"}]}}}
